{
  "verse_id": "18.65",
  "mūla": {
    "devanāgarī": "मन्मना भव मद्भक्तो मद्याजी मां नमस्कुरु | मामेवैष्यसि सत्यं ते प्रतिजाने प्रियोऽसि मे",
    "iast": "manmanā bhava madbhakto madyājī māṃ namaskuru | māmevaiṣyasi satyaṃ te pratijāne priyo'si me",
    "chapter_position": "Chapter 18 (Mokṣa-Sannyāsa-Yoga (The Yoga of Liberation by Renunciation)), verse 65",
    "speaker": "Krishna",
    "addressed_to": "Arjuna"
  },
  "word_by_word": [
    {
      "surface_form": "mad",
      "lemma": "mad",
      "grammar": "compound (compound member)",
      "senses_attested_in_panel": [],
      "theme_lists": [],
      "surface_devanagari": "मद्"
    },
    {
      "surface_form": "manāḥ",
      "lemma": "manas",
      "grammar": "nominative masculine singular noun",
      "senses_attested_in_panel": [],
      "theme_lists": [],
      "surface_devanagari": "मनाः"
    },
    {
      "surface_form": "bhava",
      "lemma": "bhū",
      "grammar": "present imperative 2nd person singular verb",
      "senses_attested_in_panel": [],
      "theme_lists": [],
      "surface_devanagari": "भव"
    },
    {
      "surface_form": "mad",
      "lemma": "mad",
      "grammar": "compound (compound member)",
      "senses_attested_in_panel": [],
      "theme_lists": [],
      "surface_devanagari": "मद्"
    },
    {
      "surface_form": "bhaktaḥ",
      "lemma": "bhakta",
      "grammar": "nominative masculine singular noun",
      "senses_attested_in_panel": [],
      "theme_lists": [],
      "surface_devanagari": "भक्तः"
    },
    {
      "surface_form": "mad",
      "lemma": "mad",
      "grammar": "compound (compound member)",
      "senses_attested_in_panel": [],
      "theme_lists": [],
      "surface_devanagari": "मद्"
    },
    {
      "surface_form": "yājī",
      "lemma": "yājin",
      "grammar": "nominative masculine singular noun",
      "senses_attested_in_panel": [],
      "theme_lists": [],
      "surface_devanagari": "याजी"
    },
    {
      "surface_form": "mām",
      "lemma": "mad",
      "grammar": "accusative singular noun",
      "senses_attested_in_panel": [],
      "theme_lists": [],
      "surface_devanagari": "माम्"
    },
    {
      "surface_form": "namaskuru",
      "lemma": "namaskṛ",
      "grammar": "present imperative 2nd person singular verb",
      "senses_attested_in_panel": [
        {
          "sense": "नमस्कारम्",
          "school": "advaita",
          "weight": 0.8,
          "witnesses": [
            "shankara"
          ]
        },
        {
          "sense": "नमो नमनं मयि अतिमात्रप्रह्वीभावम् अत्यर्थप्रियं कुरु इत्यर्थः",
          "school": "viśiṣṭādvaita",
          "weight": 0.8,
          "witnesses": [
            "ramanuja",
            "vedantadeshika"
          ]
        },
        {
          "sense": "एवं वर्तमानस्त्वं मत्प्रसादाल्लब्धज्ञानेन मामेवैष्यसि प्राप्स्यसि अत्र",
          "school": "bhakti",
          "weight": 0.8,
          "witnesses": [
            "sridhara"
          ]
        },
        {
          "sense": "कायेन वाचा मनसा",
          "school": "advaita-bhakti",
          "weight": 0.8,
          "witnesses": [
            "madhusudan"
          ]
        }
      ],
      "theme_lists": [],
      "surface_devanagari": "नमस्कुरु"
    },
    {
      "surface_form": "mām",
      "lemma": "mad",
      "grammar": "accusative singular noun",
      "senses_attested_in_panel": [],
      "theme_lists": [],
      "surface_devanagari": "माम्"
    },
    {
      "surface_form": "eva",
      "lemma": "eva",
      "grammar": "",
      "senses_attested_in_panel": [],
      "theme_lists": [],
      "surface_devanagari": "एव"
    },
    {
      "surface_form": "eṣyasi",
      "lemma": "i",
      "grammar": "future indicative 2nd person singular verb",
      "senses_attested_in_panel": [],
      "theme_lists": [],
      "surface_devanagari": "एष्यसि"
    },
    {
      "surface_form": "satyam",
      "lemma": "satya",
      "grammar": "accusative neuter singular noun",
      "senses_attested_in_panel": [],
      "theme_lists": [],
      "surface_devanagari": "सत्यम्"
    },
    {
      "surface_form": "te",
      "lemma": "tvad",
      "grammar": "dative singular noun",
      "senses_attested_in_panel": [],
      "theme_lists": [],
      "surface_devanagari": "ते"
    },
    {
      "surface_form": "pratijāne",
      "lemma": "pratijñā",
      "grammar": "present indicative 1st person singular verb",
      "senses_attested_in_panel": [
        {
          "sense": "? सत्यां प्रतिज्ञां करोमि एतस्मिन् वस्तुनि इत्यर्थः यतः प्रियः असि मे",
          "school": "advaita",
          "weight": 0.8,
          "witnesses": [
            "shankara"
          ]
        },
        {
          "sense": "तव प्रतिज्ञां करोमि? न उपच्छन्दमात्रं यतः त्वं प्रियः असि मे प्रियो हि ज्ञानिनोऽत्यर्थमहं स",
          "school": "viśiṣṭādvaita",
          "weight": 0.8,
          "witnesses": [
            "ramanuja"
          ]
        },
        {
          "sense": "सत्यं यतस्त्वं मे प्रियोऽसि",
          "school": "śuddhādvaita",
          "weight": 0.8,
          "witnesses": [
            "vallabha"
          ]
        },
        {
          "sense": "प्रतिज्ञां करोमि",
          "school": "bhakti",
          "weight": 0.8,
          "witnesses": [
            "sridhara"
          ]
        },
        {
          "sense": "सत्यामेव प्रतिज्ञां करोम्यस्मिन्नर्थे",
          "school": "advaita-bhakti",
          "weight": 0.8,
          "witnesses": [
            "madhusudan"
          ]
        }
      ],
      "theme_lists": [],
      "surface_devanagari": "प्रतिजाने"
    },
    {
      "surface_form": "priyaḥ",
      "lemma": "priya",
      "grammar": "nominative masculine singular noun",
      "senses_attested_in_panel": [],
      "theme_lists": [],
      "surface_devanagari": "प्रियः"
    },
    {
      "surface_form": "asi",
      "lemma": "as",
      "grammar": "present indicative 2nd person singular verb",
      "senses_attested_in_panel": [],
      "theme_lists": [],
      "surface_devanagari": "असि"
    },
    {
      "surface_form": "me",
      "lemma": "mad",
      "grammar": "genitive singular noun",
      "senses_attested_in_panel": [],
      "theme_lists": [],
      "surface_devanagari": "मे"
    }
  ],
  "intertextual_panel": [
    {
      "verse": "18.68",
      "type": "thematic-cluster continuation",
      "score": 0.924,
      "feature_breakdown": {
        "cosine": 0.844,
        "theme_graph": 1.0,
        "vocative": 0.0,
        "substring": 0.0,
        "lemma_overlap": 14.3175,
        "stem_prefix": 7.0
      }
    },
    {
      "verse": "17.15",
      "type": "lemma-family resonance",
      "score": 0.9123,
      "feature_breakdown": {
        "cosine": 0.8523,
        "theme_graph": 0.0,
        "vocative": 0.0,
        "substring": 0.0,
        "lemma_overlap": 12.3628,
        "stem_prefix": 6.0
      }
    },
    {
      "verse": "12.20",
      "type": "lemma-family resonance",
      "score": 0.9123,
      "feature_breakdown": {
        "cosine": 0.8523,
        "theme_graph": 0.0,
        "vocative": 0.0,
        "substring": 0.0,
        "lemma_overlap": 12.9809,
        "stem_prefix": 6.0
      }
    },
    {
      "verse": "11.49",
      "type": "lemma-family resonance",
      "score": 0.9031,
      "feature_breakdown": {
        "cosine": 0.8331,
        "theme_graph": 0.0,
        "vocative": 0.0,
        "substring": 0.0,
        "lemma_overlap": 13.9374,
        "stem_prefix": 7.0
      }
    },
    {
      "verse": "9.13",
      "type": "shared-vocabulary echo",
      "score": 0.8993,
      "feature_breakdown": {
        "cosine": 0.8493,
        "theme_graph": 0.0,
        "vocative": 0.0,
        "substring": 0.0,
        "lemma_overlap": 7.2706,
        "stem_prefix": 5.0
      }
    },
    {
      "verse": "4.3",
      "type": "lemma-family resonance",
      "score": 0.8976,
      "feature_breakdown": {
        "cosine": 0.8276,
        "theme_graph": 0.0,
        "vocative": 0.0,
        "substring": 0.0,
        "lemma_overlap": 11.9141,
        "stem_prefix": 7.0
      }
    },
    {
      "verse": "12.2",
      "type": "lemma-family resonance",
      "score": 0.8964,
      "feature_breakdown": {
        "cosine": 0.8464,
        "theme_graph": 0.0,
        "vocative": 0.0,
        "substring": 0.0,
        "lemma_overlap": 8.9607,
        "stem_prefix": 5.0
      }
    },
    {
      "verse": "9.29",
      "type": "lemma-family resonance",
      "score": 0.8958,
      "feature_breakdown": {
        "cosine": 0.8358,
        "theme_graph": 0.0,
        "vocative": 0.0,
        "substring": 0.0,
        "lemma_overlap": 14.4092,
        "stem_prefix": 6.0
      }
    }
  ],
  "doctrinal_projections": {
    "advaita": {
      "reading_summary": "(reading summary extraction pending; ENABLE_READING_SUMMARIES=true to generate)",
      "key_cross_references": [],
      "witness_passages": [
        "shankara_18.65",
        "anandgiri_18.65"
      ],
      "score": 0.5,
      "english_rendering": "Fix your mind on Me — surrender the very faculty of intention to Vasudeva. Become My devotee, My worshipper; even your bowing let it be to Me alone, so that every means (sadhana) and every end (sadhya) is given over to the Lord. Having lived thus, you will reach Me — this I promise you truly; for you are dear to Me, and a true promise (satya-pratijña) cannot be otherwise for one whose every aspiration is surrendered.",
      "commentator": "Shankaracharya"
    },
    "viśiṣṭādvaita": {
      "reading_summary": "(reading summary extraction pending; ENABLE_READING_SUMMARIES=true to generate)",
      "key_cross_references": [],
      "witness_passages": [
        "ramanuja_18.65",
        "vedantadeshika_18.65"
      ],
      "score": 0.5,
      "english_rendering": "Become one whose mind is pervaded by Me — the unbroken stream of loving memory (smriti-santana) of the kind prescribed in the Upanishads as vedana, dhyana, upasana. Your bhakti (devotion) is not mere sentiment but the fullness of sheshavrit (complete service-mode), your worship the supreme expression of that bhava. I promise you will reach Me — not as flattery (upacchandana-matra), but because your love for Me and My love for you are perfectly mutual: the one who loves Me supremely is supremely dear to Me, and I cannot bear separation from My beloved.",
      "commentator": "Ramanujacharya"
    },
    "dvaita": {
      "reading_summary": "(reading summary extraction pending; ENABLE_READING_SUMMARIES=true to generate)",
      "key_cross_references": [],
      "witness_passages": [
        "madhva_18.65",
        "jayatirtha_18.65"
      ],
      "score": 0.5,
      "english_rendering": "[BHASHYA ABSENT] The Dvaita panel commentary notes Madhvacharya did not comment on this verse. Doctrinal reconstruction from Dvaita framework: The jiva (individual soul) is eternally distinct from and dependent on Hari. 'Fixing the mind on Me' means the jiva's total ontological orientation toward Hari as the independent reality (svatantra). The fourfold injunction — mind, devotion, worship, prostration — maps the entire scope of the jiva's dependent existence (paratantra) onto service of Hari. The promise is Hari's sovereign will, not conditioned by any cosmic mechanism; the jiva's dearness to Him is a fact of Hari's svatantra grace.",
      "commentator": "Madhvacharya"
    },
    "śuddhādvaita": {
      "reading_summary": "(reading summary extraction pending; ENABLE_READING_SUMMARIES=true to generate)",
      "key_cross_references": [],
      "witness_passages": [
        "vallabha_18.65"
      ],
      "score": 0.5,
      "english_rendering": "O Partha, fix your mind on Me alone — not alongside others, but exclusively (the 'eva' particle forbids any split of attention). Be My devotee alone, My worshipper alone: these three — mind, devotion, worship — cover the full triad of sacred activity (tri-kanda). I promise you in truth: you will reach Me, for you are My beloved. A beloved is never deceived; it would be beneath Me to mislead one I love. This is the supreme path of mukhya-bhakti (principal devotion).",
      "commentator": "Vallabhacharya"
    },
    "bhakti": {
      "reading_summary": "(reading summary extraction pending; ENABLE_READING_SUMMARIES=true to generate)",
      "key_cross_references": [],
      "witness_passages": [
        "sridhara_18.65"
      ],
      "score": 0.5,
      "english_rendering": "Direct your mind to Me, let Me be your devotion, be fixed in worshipping Me, bow to Me — living thus, you will reach Me through the grace-born knowledge (mat-prasada-labdha-jñana) that My mercy kindles in you. Do not entertain any doubt here. You are My beloved, and so I make you a true promise — as things truly stand, so I declare: you will come to Me.",
      "commentator": "Sridhara Svami"
    },
    "advaita-bhakti": {
      "reading_summary": "(reading summary extraction pending; ENABLE_READING_SUMMARIES=true to generate)",
      "key_cross_references": [],
      "witness_passages": [
        "madhusudan_18.65"
      ],
      "score": 0.5,
      "english_rendering": "Let your mind be fixed in Bhagavan Vasudeva with love (premna) — not in the cold knowing of an enemy like Kamsa who also 'thought of Krsna' through hatred. Be My devotee through anuragena (affection): devotion means the mind is made into Krsna-territory by love. Worship Me always; if materials for worship are absent, bow to Me with body, speech, and mind — this bowing encompasses all nine modes of bhakti (shravana, kirtana, smarana, etc.). Living thus, by the Vedanta-generated knowledge of Me, you will come to Me at the end of prarabdha-karma. This I promise truly, for you are dear to Me, and deceiving a beloved is unworthy of the Lord.",
      "commentator": "Madhusudana Sarasvati"
    }
  },
  "prosodic_information": {
    "meter": "anuṣṭubh",
    "meter_shift_from_previous": false,
    "meter_shift_to_next": false,
    "pragmatic_context": {
      "vocative": "",
      "preceding_question": "",
      "following_response": ""
    }
  },
  "theme_list_memberships": [
    {
      "list": "मद्याजी",
      "role": "supporting",
      "other_verses_in_list": [
        "9.34"
      ]
    },
    {
      "list": "मन्मना भव",
      "role": "supporting",
      "other_verses_in_list": [
        "9.1",
        "9.34"
      ]
    },
    {
      "list": "मां नमस्कुरु",
      "role": "supporting",
      "other_verses_in_list": [
        "9.34"
      ]
    },
    {
      "list": "मामेव",
      "role": "supporting",
      "other_verses_in_list": [
        "7.14",
        "18.68"
      ]
    }
  ],
  "audit_trail": {
    "substrate_version": "v2.6-frozen",
    "fitted_weights": {
      "a": 1.0,
      "b": 0.01,
      "e_v": 0.005,
      "z": 0.2,
      "h": 0.0,
      "th": 0.01
    },
    "corpus_provenance": {
      "mūla": "Belvalkar critical edition (BORI 1947), via Ambuda multi-witness",
      "panel_witnesses": [
        "bg-mula",
        "bg-shankara",
        "bg-ramanuja",
        "bg-madhva",
        "bg-vedantadeshika",
        "bg-vallabha",
        "bg-jayatirtha",
        "bg-anandgiri",
        "bg-sridhara",
        "bg-madhusudan"
      ]
    },
    "extraction_date": "2026-04-21",
    "score_methodology_documented_at": "Paper 1, Section II.B",
    "word_by_word_parser": "ByT5-Sanskrit-multitask (Nehrdich/Hellwig/Keutzer EMNLP 2024)"
  },
  "so_what_questions": [
    "If Krsna promises 'you will reach Me' only to Arjuna because 'you are dear to Me' — is this a universal promise or a personal one, and what does that mean for practitioners who are not Arjuna?",
    "The fourfold injunction (mind, devotion, worship, prostration) is given without specifying the quality or quantity required — is the promise conditional on a threshold of practice, or is the orientation itself sufficient?",
    "Shankara reads this as preparing for samyag-darshana (right vision); Ramanuja as arriving at Vaikuntha — are these descriptions of the same attainment or genuinely different soteriological destinations?",
    "Madhusudana distinguishes love-based from hatred-based fixation on Krsna — what does this imply about the relationship between motivation and result in spiritual practice generally?",
    "If the promise is 'true' (satyam) and grounded in mutual priti (love), does this make Krsna's grace a responsive mechanism (love calls forth love) or a sovereign act (grace precedes merit)?",
    "Vallabha insists on exclusive devotion ('eva' — alone): how does this relate to the preceding chapters' pluralism about paths (karma, jñana, bhakti)? Is 18.65 a supersession or a synthesis?",
    "The verse occurs in the 'paramaguhya' (supreme secret) section of chapter 18: what makes this instruction more secret than the earlier teaching on bhakti in chapter 12?"
  ],
  "everyday_applications": {
    "advaita": "Before beginning any significant task today, pause and explicitly surrender both the goal and the means to Vasudeva — not as ritual but as a recognition that you are not the owner of either. Notice how this shifts the quality of attention during the task itself.",
    "viśiṣṭādvaita": "Maintain an unbroken thread of remembrance (smriti-santana) of the Lord throughout your day — not prayer at fixed times, but a sustained background awareness, the way a musician holds the shruti (drone) beneath the melody of daily activity.",
    "dvaita": "At moments of achievement or failure today, practice recognizing that both your capacity and the outcome belong to Hari as the independent reality (svatantra). Your role is to act as a perfectly transparent instrument, with no residue of 'I did this.'",
    "śuddhādvaita": "Choose one relationship or responsibility today and bring your full, undivided attention to it — no parallel tracking, no split loyalty. This 'eva' (exclusivity) applied to a single hour is Vallabha's pushti-marga made concrete and portable.",
    "bhakti": "When you feel doubt about whether your practice is 'working,' return to Sridhara's frame: the promise is not conditional on visible progress but on the Lord's prasada (grace). Your part is to remain oriented; the knowledge will come through the Lord's mercy, not through your measurement.",
    "advaita-bhakti": "Examine whether your attention to a person, idea, or goal you are 'devoted to' today is prema-yukta (love-informed) or dwesa-yukta (anxiety-driven). Madhusudana's distinction: both can generate obsessive focus, but only one qualifies as bhakti — what is the texture of your attention?"
  }
}
