{
  "verse_id": "1.34",
  "mūla": {
    "devanāgarī": "आचार्याः पितरः पुत्रास् तथैव च पितामहाः | मातुलाः श्वशुराः पौत्राः श्यालाः संबन्धिनस् तथा",
    "iast": "ācāryāḥ pitaraḥ putrās tathaiva ca pitāmahāḥ | mātulāḥ śvaśurāḥ pautrāḥ śyālāḥ saṃbandhinas tathā",
    "chapter_position": "Chapter 1 (Arjuna-Viṣāda-Yoga (The Yoga of Arjuna's Despondency)), verse 34",
    "speaker": "Arjuna",
    "addressed_to": "Krishna"
  },
  "word_by_word": [
    {
      "surface_form": "ācāryās",
      "lemma": "ācar",
      "grammar": "nominative plural masculine noun",
      "senses_attested_in_panel": [],
      "theme_lists": []
    },
    {
      "surface_form": "pitaras",
      "lemma": "pitṛ",
      "grammar": "nominative plural masculine noun",
      "senses_attested_in_panel": [],
      "theme_lists": []
    },
    {
      "surface_form": "putrās",
      "lemma": "putra",
      "grammar": "nominative plural masculine noun",
      "senses_attested_in_panel": [],
      "theme_lists": []
    },
    {
      "surface_form": "tathā",
      "lemma": "tathā",
      "grammar": "nominative singular masculine noun",
      "senses_attested_in_panel": [],
      "theme_lists": []
    },
    {
      "surface_form": "eva",
      "lemma": "eva",
      "grammar": "vocative singular neuter noun",
      "senses_attested_in_panel": [],
      "theme_lists": []
    },
    {
      "surface_form": "ca",
      "lemma": "ca",
      "grammar": "vocative singular masculine noun",
      "senses_attested_in_panel": [
        {
          "sense": "्युतिं प्रदर्शयति एतानिति",
          "school": "advaita",
          "weight": 1.0,
          "witnesses": [
            "anandgiri"
          ]
        },
        {
          "sense": "संजय उवाच स तु पार्थो महामनाः परमकारुणिको दीर्घबन्धुः परमधार्मिकः सभ्रातृको भवद्भिः अतिघोरैः मारणैः जतुगृहादिभिः असकृद्",
          "school": "viśiṣṭādvaita",
          "weight": 1.0,
          "witnesses": [
            "ramanuja"
          ]
        },
        {
          "sense": "्छामि। किं पुनर्महीमात्रप्राप्त्यर्थमित्यर्थः।",
          "school": "bhakti",
          "weight": 1.0,
          "witnesses": [
            "sridhara"
          ]
        },
        {
          "sense": "्छामि इच्छामपि न कुर्यामहं किं पुनर्हन्याम् महीमात्रप्राप्तये तु न हन्यामिति किमु वक्तव्यमित्यर्थः",
          "school": "advaita-bhakti",
          "weight": 1.0,
          "witnesses": [
            "madhusudan"
          ]
        }
      ],
      "theme_lists": [
        "आचार्य",
        "आचार्याः",
        "आचार्याः पितरः৷৷ किं नु महीकृते",
        "है और सुखभोगकी इच्छाका नाम"
      ]
    },
    {
      "surface_form": "pitāmahās",
      "lemma": "pitāmaha",
      "grammar": "nominative plural masculine noun",
      "senses_attested_in_panel": [],
      "theme_lists": []
    },
    {
      "surface_form": "mātulās",
      "lemma": "mātula",
      "grammar": "nominative plural masculine noun",
      "senses_attested_in_panel": [],
      "theme_lists": []
    },
    {
      "surface_form": "śvaśurās",
      "lemma": "śvaśura",
      "grammar": "nominative plural masculine noun",
      "senses_attested_in_panel": [],
      "theme_lists": []
    },
    {
      "surface_form": "pā",
      "lemma": "pā",
      "grammar": "vocative singular neuter noun",
      "senses_attested_in_panel": [
        {
          "sense": "बुद्ध्या स्वधर्माद्युद्धात्पूर्वोक्तमोहादिवशात्प्रच्युतिं प्रदर्शयति एतानिति",
          "school": "advaita",
          "weight": 1.0,
          "witnesses": [
            "anandgiri"
          ]
        },
        {
          "sense": "र्थो महामनाः परमकारुणिको दीर्घबन्धुः परमधार्मिकः सभ्रातृको भवद्भिः अतिघोरैः मारणैः जतुगृहादिभिः असकृद् वञ्चितः",
          "school": "viśiṣṭādvaita",
          "weight": 1.0,
          "witnesses": [
            "ramanuja"
          ]
        }
      ],
      "theme_lists": []
    },
    {
      "surface_form": "otrā",
      "lemma": "u",
      "grammar": "instrumental singular masculine noun",
      "senses_attested_in_panel": [],
      "theme_lists": []
    },
    {
      "surface_form": "as",
      "lemma": "a",
      "grammar": "nominative singular masculine noun",
      "senses_attested_in_panel": [
        {
          "sense": "मान्घ्नतोऽप्येतान्न हन्तुमिच्छामि इच्छामपि न कुर्यामहं किं पुनर्हन्याम् महीमात्रप्राप्तये तु न हन्यामिति किमु वक्तव्यमित",
          "school": "advaita-bhakti",
          "weight": 1.0,
          "witnesses": [
            "madhusudan"
          ]
        }
      ],
      "theme_lists": []
    },
    {
      "surface_form": "śi",
      "lemma": "śī",
      "grammar": "vocative singular feminine noun",
      "senses_attested_in_panel": [
        {
          "sense": "नष्टि स्पष्टम्",
          "school": "advaita-bhakti",
          "weight": 1.0,
          "witnesses": [
            "madhusudan"
          ]
        }
      ],
      "theme_lists": []
    },
    {
      "surface_form": "ālās",
      "lemma": "āli",
      "grammar": "nominative plural masculine noun",
      "senses_attested_in_panel": [],
      "theme_lists": []
    },
    {
      "surface_form": "sam",
      "lemma": "sa",
      "grammar": "accusative singular masculine noun",
      "senses_attested_in_panel": [],
      "theme_lists": [
        "सम्बन्धिनः"
      ]
    },
    {
      "surface_form": "bandhinas",
      "lemma": "bandh",
      "grammar": "nominative plural masculine noun",
      "senses_attested_in_panel": [],
      "theme_lists": []
    },
    {
      "surface_form": "tathā",
      "lemma": "tathā",
      "grammar": "nominative singular masculine noun",
      "senses_attested_in_panel": [],
      "theme_lists": []
    }
  ],
  "intertextual_panel": [
    {
      "verse": "1.26",
      "type": "thematic-similarity",
      "score": 0.9771,
      "feature_breakdown": {
        "cosine": 0.8659,
        "theme_graph": 2.0,
        "vocative": 0.0,
        "substring": 0.0563,
        "lemma_overlap": 35.0699,
        "stem_prefix": 8.0
      }
    },
    {
      "verse": "1.35",
      "type": "thematic-similarity",
      "score": 0.9208,
      "feature_breakdown": {
        "cosine": 0.7808,
        "theme_graph": 13.0,
        "vocative": 0.0,
        "substring": 0.0,
        "lemma_overlap": 0.7751,
        "stem_prefix": 1.0
      }
    },
    {
      "verse": "11.26",
      "type": "thematic-similarity",
      "score": 0.889,
      "feature_breakdown": {
        "cosine": 0.829,
        "theme_graph": 1.0,
        "vocative": 0.0,
        "substring": 0.0,
        "lemma_overlap": 11.0221,
        "stem_prefix": 5.0
      }
    },
    {
      "verse": "1.3",
      "type": "thematic-similarity",
      "score": 0.8875,
      "feature_breakdown": {
        "cosine": 0.8479,
        "theme_graph": 1.0,
        "vocative": 0.0,
        "substring": 0.0483,
        "lemma_overlap": 8.6685,
        "stem_prefix": 2.0
      }
    },
    {
      "verse": "1.42",
      "type": "thematic-similarity",
      "score": 0.8849,
      "feature_breakdown": {
        "cosine": 0.8449,
        "theme_graph": 0.0,
        "vocative": 0.0,
        "substring": 0.0,
        "lemma_overlap": 8.505,
        "stem_prefix": 4.0
      }
    },
    {
      "verse": "1.27",
      "type": "thematic-similarity",
      "score": 0.879,
      "feature_breakdown": {
        "cosine": 0.819,
        "theme_graph": 0.0,
        "vocative": 0.0,
        "substring": 0.0,
        "lemma_overlap": 14.8428,
        "stem_prefix": 6.0
      }
    },
    {
      "verse": "9.30",
      "type": "thematic-similarity",
      "score": 0.8671,
      "feature_breakdown": {
        "cosine": 0.8071,
        "theme_graph": 0.0,
        "vocative": 0.0,
        "substring": 0.0,
        "lemma_overlap": 10.9044,
        "stem_prefix": 6.0
      }
    },
    {
      "verse": "13.9",
      "type": "thematic-similarity",
      "score": 0.8669,
      "feature_breakdown": {
        "cosine": 0.8369,
        "theme_graph": 0.0,
        "vocative": 0.0,
        "substring": 0.0,
        "lemma_overlap": 6.6062,
        "stem_prefix": 3.0
      }
    }
  ],
  "doctrinal_projections": {
    "advaita": {
      "reading_summary": "(reading summary extraction forthcoming in next-pass build)",
      "key_cross_references": [],
      "witness_passages": [
        "shankara_1.34",
        "anandgiri_1.34"
      ],
      "score": 0.5
    },
    "viśiṣṭādvaita": {
      "reading_summary": "(reading summary extraction forthcoming in next-pass build)",
      "key_cross_references": [],
      "witness_passages": [
        "ramanuja_1.34",
        "vedantadeshika_1.34"
      ],
      "score": 0.5
    },
    "śuddhādvaita": {
      "reading_summary": "(reading summary extraction forthcoming in next-pass build)",
      "key_cross_references": [],
      "witness_passages": [
        "vallabha_1.34"
      ],
      "score": 0.5
    },
    "bhakti": {
      "reading_summary": "(reading summary extraction forthcoming in next-pass build)",
      "key_cross_references": [],
      "witness_passages": [
        "sridhara_1.34"
      ],
      "score": 0.5
    },
    "advaita-bhakti": {
      "reading_summary": "(reading summary extraction forthcoming in next-pass build)",
      "key_cross_references": [],
      "witness_passages": [
        "madhusudan_1.34"
      ],
      "score": 0.5
    }
  },
  "prosodic_information": {
    "meter": "anuṣṭubh",
    "meter_shift_from_previous": false,
    "meter_shift_to_next": true,
    "pragmatic_context": {
      "vocative": "",
      "preceding_question": "",
      "following_response": ""
    }
  },
  "theme_list_memberships": [
    {
      "list": "आचार्य",
      "role": "supporting",
      "other_verses_in_list": [
        "1.2",
        "1.3",
        "1.26",
        "6.44",
        "13.7"
      ]
    },
    {
      "list": "आचार्याः",
      "role": "supporting",
      "other_verses_in_list": [
        "1.35"
      ]
    },
    {
      "list": "आचार्याः पितरः৷৷ किं नु महीकृते",
      "role": "supporting",
      "other_verses_in_list": [
        "1.35"
      ]
    },
    {
      "list": "क्रोध",
      "role": "supporting",
      "other_verses_in_list": [
        "1.35",
        "2.56",
        "2.62",
        "2.63",
        "3.37",
        "3.40",
        "4.10",
        "5.23",
        "5.26",
        "5.28",
        "16.2",
        "16.4",
        "16.12",
        "16.18",
        "16.21",
        "18.53"
      ]
    },
    {
      "list": "पितरः",
      "role": "supporting",
      "other_verses_in_list": [
        "1.35"
      ]
    },
    {
      "list": "पितामह",
      "role": "supporting",
      "other_verses_in_list": [
        "1.12",
        "1.26",
        "9.16",
        "9.17",
        "9.18",
        "11.39"
      ]
    },
    {
      "list": "पितामहाः",
      "role": "supporting",
      "other_verses_in_list": [
        "1.35"
      ]
    },
    {
      "list": "पुत्राः",
      "role": "supporting",
      "other_verses_in_list": [
        "1.35",
        "11.26"
      ]
    },
    {
      "list": "पौत्राः",
      "role": "supporting",
      "other_verses_in_list": [
        "1.35"
      ]
    },
    {
      "list": "मधूसूदन",
      "role": "supporting",
      "other_verses_in_list": [
        "1.35"
      ]
    },
    {
      "list": "मातुलाः",
      "role": "supporting",
      "other_verses_in_list": [
        "1.35"
      ]
    },
    {
      "list": "श्यालाः",
      "role": "supporting",
      "other_verses_in_list": [
        "1.35"
      ]
    },
    {
      "list": "श्वशुराः",
      "role": "supporting",
      "other_verses_in_list": [
        "1.35"
      ]
    },
    {
      "list": "सम्बन्धिनः",
      "role": "supporting",
      "other_verses_in_list": [
        "1.35"
      ]
    },
    {
      "list": "है और सुखभोगकी इच्छाका नाम",
      "role": "supporting",
      "other_verses_in_list": [
        "1.35"
      ]
    }
  ],
  "audit_trail": {
    "substrate_version": "v2.6-frozen",
    "fitted_weights": {
      "a": 1.0,
      "b": 0.01,
      "e_v": 0.005,
      "z": 0.2,
      "h": 0.0,
      "th": 0.01
    },
    "corpus_provenance": {
      "mūla": "Belvalkar critical edition (BORI 1947), via Ambuda multi-witness",
      "panel_witnesses": [
        "bg-mula",
        "bg-shankara",
        "bg-ramanuja",
        "bg-madhva",
        "bg-vedantadeshika",
        "bg-vallabha",
        "bg-jayatirtha",
        "bg-anandgiri",
        "bg-sridhara",
        "bg-madhusudan"
      ]
    },
    "extraction_date": "2026-04-21",
    "score_methodology_documented_at": "Paper 1, Section II.B"
  }
}