{
  "verse_id": "13.13",
  "mūla": {
    "devanāgarī": "सर्वतः पाणि-पादं तत् सर्वतो ऽक्षि-शिरो-मुखम् | सर्वतः श्रुतिमल् लोके सर्वम् आवृत्य तिष्ठति",
    "iast": "sarvataḥ pāṇi-pādaṃ tat sarvato 'kṣi-śiro-mukham | sarvataḥ śrutimal loke sarvam āvṛtya tiṣṭhati",
    "chapter_position": "Chapter 13 (Kṣetra-Kṣetrajña-Vibhāga-Yoga (The Yoga of Distinction Between Field and Field-Knower)), verse 13",
    "speaker": "Krishna",
    "addressed_to": "Arjuna"
  },
  "word_by_word": [
    {
      "surface_form": "sarvatas",
      "lemma": "sarvatas",
      "grammar": "nominative singular masculine noun",
      "senses_attested_in_panel": [],
      "theme_lists": []
    },
    {
      "surface_form": "pāṇi",
      "lemma": "paṇāyi",
      "grammar": "locative singular masculine noun",
      "senses_attested_in_panel": [
        {
          "sense": "पादमस्येति कथं पाणीनां",
          "school": "advaita",
          "weight": 1.0,
          "witnesses": [
            "anandgiri"
          ]
        },
        {
          "sense": "पादं तत् परिशुद्धात्मस्वरूपं सर्वतःपाणिपादकार्यशक्तम्? तथा सर्वतोऽक्षिशिरोमुखम् सर्वतःश्रुतिमत् सर्वतश्चक्षुरादिकार्यकृत",
          "school": "viśiṣṭādvaita",
          "weight": 1.0,
          "witnesses": [
            "ramanuja"
          ]
        }
      ],
      "theme_lists": []
    },
    {
      "surface_form": "pādam",
      "lemma": "pad",
      "grammar": "accusative singular masculine noun",
      "senses_attested_in_panel": [],
      "theme_lists": []
    },
    {
      "surface_form": "tat",
      "lemma": "tad",
      "grammar": "vocative singular neuter noun",
      "senses_attested_in_panel": [
        {
          "sense": "प्रवक्ष्यामि प्रकर्षेण यथावत् वक्ष्यामि",
          "school": "advaita",
          "weight": 0.5,
          "witnesses": [
            "shankara",
            "anandgiri"
          ]
        },
        {
          "sense": "परिशुद्धात्मस्वरूपं सर्वतःपाणिपादकार्यशक्तम्? तथा सर्वतोऽक्षिशिरोमुखम् सर्वतःश्रुतिमत् सर्वतश्चक्षुरादिकार्यकृत् --,अपा",
          "school": "viśiṣṭādvaita",
          "weight": 0.5,
          "witnesses": [
            "ramanuja",
            "vedantadeshika"
          ]
        },
        {
          "sense": "इत्यादिकं वाक्यमिति सूचितम्? तत्र केन तु किमुच्यते इत्यत आह -- परमि ति",
          "school": "dvaita",
          "weight": 1.0,
          "witnesses": [
            "jayatirtha"
          ]
        },
        {
          "sense": "प्रवक्ष्यामि",
          "school": "bhakti",
          "weight": 1.0,
          "witnesses": [
            "sridhara"
          ]
        },
        {
          "sense": "प्रवक्ष्यामि प्रकर्षेण स्पष्टतया वक्ष्यामि",
          "school": "advaita-bhakti",
          "weight": 1.0,
          "witnesses": [
            "madhusudan"
          ]
        }
      ],
      "theme_lists": []
    },
    {
      "surface_form": "sarvatas",
      "lemma": "sarvatas",
      "grammar": "nominative singular masculine noun",
      "senses_attested_in_panel": [],
      "theme_lists": []
    },
    {
      "surface_form": "akṣi",
      "lemma": "akṣi",
      "grammar": "nominative singular neuter noun",
      "senses_attested_in_panel": [
        {
          "sense": "श्रवणवत्त्वमवशिष्टज्ञानेन्द्रियवत्त्वस्य पाणिपादमुखवत्त्वं चावशिष्टकर्मेन्द्रियवत्त्वस्य मनोबुद्ध्यादिमत्त्वस्य चोपलक्षण",
          "school": "advaita",
          "weight": 1.0,
          "witnesses": [
            "anandgiri"
          ]
        }
      ],
      "theme_lists": []
    },
    {
      "surface_form": "śis",
      "lemma": "śās",
      "grammar": "vocative singular neuter noun",
      "senses_attested_in_panel": [],
      "theme_lists": []
    },
    {
      "surface_form": "o",
      "lemma": "u",
      "grammar": "vocative singular masculine noun",
      "senses_attested_in_panel": [],
      "theme_lists": []
    },
    {
      "surface_form": "mukham",
      "lemma": "mukha",
      "grammar": "nominative singular neuter noun",
      "senses_attested_in_panel": [
        {
          "sense": "सर्वतःश्रुतिमत् सर्वतश्चक्षुरादिकार्यकृत् --,अपाणिपादो जवनो ग्रहीता पश्यत्यचक्षुः स श्रृणोत्यकर्णः (श्वे0 उ 0 3",
          "school": "viśiṣṭādvaita",
          "weight": 1.0,
          "witnesses": [
            "ramanuja"
          ]
        }
      ],
      "theme_lists": []
    },
    {
      "surface_form": "sarvatas",
      "lemma": "sarvatas",
      "grammar": "nominative singular masculine noun",
      "senses_attested_in_panel": [],
      "theme_lists": []
    },
    {
      "surface_form": "śrutimat",
      "lemma": "śrutimat",
      "grammar": "vocative singular neuter noun",
      "senses_attested_in_panel": [
        {
          "sense": "सर्वतश्चक्षुरादिकार्यकृत् --,अपाणिपादो जवनो ग्रहीता पश्यत्यचक्षुः स श्रृणोत्यकर्णः (श्वे0 उ 0 3",
          "school": "viśiṣṭādvaita",
          "weight": 1.0,
          "witnesses": [
            "ramanuja"
          ]
        }
      ],
      "theme_lists": []
    },
    {
      "surface_form": "loke",
      "lemma": "lok",
      "grammar": "1st person singular present indicative active verb",
      "senses_attested_in_panel": [
        {
          "sense": "ऽस्ति वा न वेति (तै0 सं0 6",
          "school": "advaita",
          "weight": 1.0,
          "witnesses": [
            "shankara"
          ]
        },
        {
          "sense": "सर्वम् आवृत्य तिष्ठति इति",
          "school": "viśiṣṭādvaita",
          "weight": 0.5,
          "witnesses": [
            "ramanuja",
            "vedantadeshika"
          ]
        }
      ],
      "theme_lists": []
    },
    {
      "surface_form": "sarvam",
      "lemma": "sarva",
      "grammar": "accusative singular masculine noun",
      "senses_attested_in_panel": [
        {
          "sense": "आवृत्य तिष्ठति इति",
          "school": "viśiṣṭādvaita",
          "weight": 1.0,
          "witnesses": [
            "ramanuja"
          ]
        }
      ],
      "theme_lists": [
        "सर्वम्"
      ]
    },
    {
      "surface_form": "āvṛtya",
      "lemma": "āvṛ",
      "grammar": "nominative singular masculine noun",
      "senses_attested_in_panel": [
        {
          "sense": "तिष्ठति इति",
          "school": "viśiṣṭādvaita",
          "weight": 1.0,
          "witnesses": [
            "ramanuja"
          ]
        }
      ],
      "theme_lists": []
    },
    {
      "surface_form": "tiṣṭhati",
      "lemma": "sthā",
      "grammar": "3rd person singular present indicative active verb",
      "senses_attested_in_panel": [
        {
          "sense": "इति। लोके यद् वस्तुजातं तत् सर्वं व्याप्य तिष्ठति परिशुद्धस्वरूपं देशादिपरिच्छेदरहिततया सर्वगतम् इत्यर्थः।।",
          "school": "viśiṣṭādvaita",
          "weight": 1.0,
          "witnesses": [
            "ramanuja"
          ]
        }
      ],
      "theme_lists": [
        "तिष्ठति"
      ]
    }
  ],
  "intertextual_panel": [
    {
      "verse": "9.6",
      "type": "thematic-similarity",
      "score": 0.8749,
      "feature_breakdown": {
        "cosine": 0.8449,
        "theme_graph": 0.0,
        "vocative": 0.0,
        "substring": 0.0,
        "lemma_overlap": 4.9584,
        "stem_prefix": 3.0
      }
    },
    {
      "verse": "2.53",
      "type": "thematic-similarity",
      "score": 0.8744,
      "feature_breakdown": {
        "cosine": 0.8444,
        "theme_graph": 1.0,
        "vocative": 0.0,
        "substring": 0.0,
        "lemma_overlap": 2.8861,
        "stem_prefix": 2.0
      }
    },
    {
      "verse": "15.16",
      "type": "thematic-similarity",
      "score": 0.8699,
      "feature_breakdown": {
        "cosine": 0.8399,
        "theme_graph": 0.0,
        "vocative": 0.0,
        "substring": 0.0,
        "lemma_overlap": 3.1157,
        "stem_prefix": 3.0
      }
    },
    {
      "verse": "4.33",
      "type": "thematic-similarity",
      "score": 0.868,
      "feature_breakdown": {
        "cosine": 0.838,
        "theme_graph": 1.0,
        "vocative": 0.0,
        "substring": 0.0,
        "lemma_overlap": 2.0279,
        "stem_prefix": 2.0
      }
    },
    {
      "verse": "5.29",
      "type": "thematic-similarity",
      "score": 0.8676,
      "feature_breakdown": {
        "cosine": 0.8476,
        "theme_graph": 0.0,
        "vocative": 0.0,
        "substring": 0.0,
        "lemma_overlap": 5.1435,
        "stem_prefix": 2.0
      }
    },
    {
      "verse": "17.7",
      "type": "thematic-similarity",
      "score": 0.867,
      "feature_breakdown": {
        "cosine": 0.837,
        "theme_graph": 0.0,
        "vocative": 0.0,
        "substring": 0.0,
        "lemma_overlap": 3.859,
        "stem_prefix": 3.0
      }
    },
    {
      "verse": "6.29",
      "type": "thematic-similarity",
      "score": 0.8669,
      "feature_breakdown": {
        "cosine": 0.8469,
        "theme_graph": 0.0,
        "vocative": 0.0,
        "substring": 0.0,
        "lemma_overlap": 2.0279,
        "stem_prefix": 2.0
      }
    },
    {
      "verse": "14.11",
      "type": "thematic-similarity",
      "score": 0.8664,
      "feature_breakdown": {
        "cosine": 0.8464,
        "theme_graph": 0.0,
        "vocative": 0.0,
        "substring": 0.0,
        "lemma_overlap": 4.1002,
        "stem_prefix": 2.0
      }
    }
  ],
  "doctrinal_projections": {
    "advaita": {
      "reading_summary": "(reading summary extraction forthcoming in next-pass build)",
      "key_cross_references": [],
      "witness_passages": [
        "shankara_13.13",
        "anandgiri_13.13"
      ],
      "score": 0.5
    },
    "viśiṣṭādvaita": {
      "reading_summary": "(reading summary extraction forthcoming in next-pass build)",
      "key_cross_references": [],
      "witness_passages": [
        "ramanuja_13.13",
        "vedantadeshika_13.13"
      ],
      "score": 0.5
    },
    "dvaita": {
      "reading_summary": "(reading summary extraction forthcoming in next-pass build)",
      "key_cross_references": [],
      "witness_passages": [
        "madhva_13.13",
        "jayatirtha_13.13"
      ],
      "score": 0.5
    },
    "śuddhādvaita": {
      "reading_summary": "(reading summary extraction forthcoming in next-pass build)",
      "key_cross_references": [],
      "witness_passages": [
        "vallabha_13.13"
      ],
      "score": 0.5
    },
    "bhakti": {
      "reading_summary": "(reading summary extraction forthcoming in next-pass build)",
      "key_cross_references": [],
      "witness_passages": [
        "sridhara_13.13"
      ],
      "score": 0.5
    },
    "advaita-bhakti": {
      "reading_summary": "(reading summary extraction forthcoming in next-pass build)",
      "key_cross_references": [],
      "witness_passages": [
        "madhusudan_13.13"
      ],
      "score": 0.5
    }
  },
  "prosodic_information": {
    "meter": "anuṣṭubh",
    "meter_shift_from_previous": false,
    "meter_shift_to_next": false,
    "pragmatic_context": {
      "vocative": "",
      "preceding_question": "",
      "following_response": ""
    }
  },
  "theme_list_memberships": [
    {
      "list": "तिष्ठति",
      "role": "supporting",
      "other_verses_in_list": [
        "3.18",
        "14.23",
        "18.61"
      ]
    },
    {
      "list": "श्रुत",
      "role": "supporting",
      "other_verses_in_list": [
        "2.29",
        "2.52",
        "2.53",
        "11.2",
        "13.25"
      ]
    },
    {
      "list": "सर्वम्",
      "role": "supporting",
      "other_verses_in_list": [
        "2.17",
        "4.33",
        "7.7",
        "7.13",
        "7.19",
        "8.22",
        "8.28",
        "10.8",
        "10.14"
      ]
    }
  ],
  "audit_trail": {
    "substrate_version": "v2.6-frozen",
    "fitted_weights": {
      "a": 1.0,
      "b": 0.01,
      "e_v": 0.005,
      "z": 0.2,
      "h": 0.0,
      "th": 0.01
    },
    "corpus_provenance": {
      "mūla": "Belvalkar critical edition (BORI 1947), via Ambuda multi-witness",
      "panel_witnesses": [
        "bg-mula",
        "bg-shankara",
        "bg-ramanuja",
        "bg-madhva",
        "bg-vedantadeshika",
        "bg-vallabha",
        "bg-jayatirtha",
        "bg-anandgiri",
        "bg-sridhara",
        "bg-madhusudan"
      ]
    },
    "extraction_date": "2026-04-21",
    "score_methodology_documented_at": "Paper 1, Section II.B"
  }
}