{
  "verse_id": "10.35",
  "mūla": {
    "devanāgarī": "बृहत्-साम तथा साम्नां गायत्री छन्दसाम् अहम् | मासानां मार्गशीर्षो ऽहम् ऋतूनां कुसुमाकरः",
    "iast": "bṛhat-sāma tathā sāmnāṃ gāyatrī chandasām aham | māsānāṃ mārgaśīrṣo 'ham ṛtūnāṃ kusumākaraḥ",
    "chapter_position": "Chapter 10 (Vibhūti-Yoga (The Yoga of Divine Manifestations)), verse 35",
    "speaker": "Krishna",
    "addressed_to": "Arjuna"
  },
  "word_by_word": [
    {
      "surface_form": "bṛhat",
      "lemma": "bṛhat",
      "grammar": "nominative singular masculine noun",
      "senses_attested_in_panel": [
        {
          "sense": "साम तथा साम्नां प्रधानमस्मि",
          "school": "advaita",
          "weight": 1.0,
          "witnesses": [
            "shankara"
          ]
        },
        {
          "sense": "साम अहम्? छन्दसां गायत्रीं अहम्? ऋतूनां कुसुमाकरः वसन्तः",
          "school": "viśiṣṭādvaita",
          "weight": 0.5,
          "witnesses": [
            "ramanuja",
            "vedantadeshika"
          ]
        },
        {
          "sense": "सामेति",
          "school": "śuddhādvaita",
          "weight": 1.0,
          "witnesses": [
            "vallabha"
          ]
        },
        {
          "sense": "सामेति",
          "school": "bhakti",
          "weight": 1.0,
          "witnesses": [
            "sridhara"
          ]
        },
        {
          "sense": "साम। तच्चातिरात्रे पृष्ठस्तोत्रं सर्वेश्वरत्वेनेन्द्रस्तुतिरूपमन्यतः श्रेष्ठत्वादहम्। छन्दसां नियताक्षरपादत्वरूपच्छन्दोव",
          "school": "advaita-bhakti",
          "weight": 1.0,
          "witnesses": [
            "madhusudan"
          ]
        }
      ],
      "theme_lists": []
    },
    {
      "surface_form": "sāma",
      "lemma": "sāmi",
      "grammar": "vocative singular masculine noun",
      "senses_attested_in_panel": [
        {
          "sense": "तथा साम्नां प्रधानमस्मि",
          "school": "advaita",
          "weight": 0.5,
          "witnesses": [
            "shankara",
            "anandgiri"
          ]
        },
        {
          "sense": "्नां बृहत्साम अहम्? छन्दसां गायत्रीं अहम्? ऋतूनां कुसुमाकरः वसन्तः",
          "school": "viśiṣṭādvaita",
          "weight": 0.5,
          "witnesses": [
            "ramanuja",
            "vedantadeshika"
          ]
        },
        {
          "sense": "ेति। त्वामिद्धि हवामहे [ऋक्सं.4।7।21।1] इत्यस्यां ऋचि गीयमानं बृहत्साम तेन चेन्द्रः सर्वेश्वरत्वेन स्तूयत इति श्रैठ्यं द",
          "school": "śuddhādvaita",
          "weight": 1.0,
          "witnesses": [
            "vallabha"
          ]
        },
        {
          "sense": "ेति। त्वामिद्धि हवामहे इत्यस्यामृचि गीयमानं बृहत्साम तेन चेन्द्रः सर्वेश्वरत्वेन स्तूयत इति श्रैष्ठ्यं दर्शितम्। छन्दोवि",
          "school": "bhakti",
          "weight": 1.0,
          "witnesses": [
            "sridhara"
          ]
        },
        {
          "sense": "वेदोऽस्मीत्युक्तं तत्रायमन्यो विशेषः",
          "school": "advaita-bhakti",
          "weight": 1.0,
          "witnesses": [
            "madhusudan"
          ]
        }
      ],
      "theme_lists": []
    },
    {
      "surface_form": "tathā",
      "lemma": "tathā",
      "grammar": "nominative singular masculine noun",
      "senses_attested_in_panel": [
        {
          "sense": "साम्नां प्रधानमस्मि",
          "school": "advaita",
          "weight": 1.0,
          "witnesses": [
            "shankara"
          ]
        }
      ],
      "theme_lists": []
    },
    {
      "surface_form": "sām",
      "lemma": "sā",
      "grammar": "accusative singular feminine noun",
      "senses_attested_in_panel": [
        {
          "sense": "नां प्रधानमस्मि",
          "school": "advaita",
          "weight": 1.0,
          "witnesses": [
            "shankara"
          ]
        },
        {
          "sense": "नां बृहत्साम अहम्? छन्दसां गायत्रीं अहम्? ऋतूनां कुसुमाकरः वसन्तः",
          "school": "viśiṣṭādvaita",
          "weight": 0.5,
          "witnesses": [
            "ramanuja",
            "vedantadeshika"
          ]
        },
        {
          "sense": "रामृगक्षरारूढानां गीतिविशेषाणां मध्येत्वामिद्धि हवामहे इत्यस्यामृचि गीतिविशेषो बृहत्साम",
          "school": "advaita-bhakti",
          "weight": 1.0,
          "witnesses": [
            "madhusudan"
          ]
        }
      ],
      "theme_lists": []
    },
    {
      "surface_form": "nām",
      "lemma": "na",
      "grammar": "accusative singular feminine noun",
      "senses_attested_in_panel": [],
      "theme_lists": []
    },
    {
      "surface_form": "gāyatrī",
      "lemma": "gāyatrī",
      "grammar": "nominative singular feminine noun",
      "senses_attested_in_panel": [
        {
          "sense": "च्छन्दसाम् अहं गायत्र्यादिच्छन्दोविशिष्टानामृचां गायत्री ऋक् अहम् अस्मि इत्यर्थः",
          "school": "advaita",
          "weight": 0.5,
          "witnesses": [
            "shankara",
            "anandgiri"
          ]
        },
        {
          "sense": "ं अहम्? ऋतूनां कुसुमाकरः वसन्तः",
          "school": "viśiṣṭādvaita",
          "weight": 0.5,
          "witnesses": [
            "ramanuja",
            "vedantadeshika"
          ]
        },
        {
          "sense": "मे विभूतिः? मत्स्वरूपप्रतिपादकत्वाद्भगवत्सेवकैश्चिन्तनीया",
          "school": "śuddhādvaita",
          "weight": 1.0,
          "witnesses": [
            "vallabha"
          ]
        },
        {
          "sense": "ऋगहम्",
          "school": "advaita-bhakti",
          "weight": 1.0,
          "witnesses": [
            "madhusudan"
          ]
        }
      ],
      "theme_lists": []
    },
    {
      "surface_form": "chandasām",
      "lemma": "chandas",
      "grammar": "Vibhakti.Sasthi plural neuter noun",
      "senses_attested_in_panel": [
        {
          "sense": "अहं गायत्र्यादिच्छन्दोविशिष्टानामृचां गायत्री ऋक् अहम् अस्मि इत्यर्थः",
          "school": "advaita",
          "weight": 1.0,
          "witnesses": [
            "shankara"
          ]
        }
      ],
      "theme_lists": []
    },
    {
      "surface_form": "aham",
      "lemma": "aha",
      "grammar": "nominative singular neuter noun",
      "senses_attested_in_panel": [
        {
          "sense": "अस्मि इत्यर्थः",
          "school": "advaita",
          "weight": 1.0,
          "witnesses": [
            "shankara"
          ]
        },
        {
          "sense": "? छन्दसां गायत्रीं अहम्? ऋतूनां कुसुमाकरः वसन्तः",
          "school": "viśiṣṭādvaita",
          "weight": 1.0,
          "witnesses": [
            "ramanuja"
          ]
        }
      ],
      "theme_lists": []
    },
    {
      "surface_form": "māsānām",
      "lemma": "māsa",
      "grammar": "Vibhakti.Sasthi plural masculine noun",
      "senses_attested_in_panel": [],
      "theme_lists": []
    },
    {
      "surface_form": "mārgaśīrṣas",
      "lemma": "mārgaśīrṣa",
      "grammar": "nominative singular masculine noun",
      "senses_attested_in_panel": [
        {
          "sense": "यातिशयः वर्षगर्भाधानकालत्वान्मासाधिदेवेषु केशवादिषु प्रथमस्य केशवस्य मासत्वाद्ब्रतवर्गारम्भकालत्वाच्च",
          "school": "viśiṣṭādvaita",
          "weight": 1.0,
          "witnesses": [
            "vedantadeshika"
          ]
        }
      ],
      "theme_lists": []
    },
    {
      "surface_form": "aham",
      "lemma": "aha",
      "grammar": "nominative singular neuter noun",
      "senses_attested_in_panel": [
        {
          "sense": "अस्मि इत्यर्थः",
          "school": "advaita",
          "weight": 1.0,
          "witnesses": [
            "shankara"
          ]
        },
        {
          "sense": "? छन्दसां गायत्रीं अहम्? ऋतूनां कुसुमाकरः वसन्तः",
          "school": "viśiṣṭādvaita",
          "weight": 1.0,
          "witnesses": [
            "ramanuja"
          ]
        }
      ],
      "theme_lists": []
    },
    {
      "surface_form": "ṛtūnām",
      "lemma": "ṛtu",
      "grammar": "Vibhakti.Sasthi plural masculine noun",
      "senses_attested_in_panel": [],
      "theme_lists": []
    },
    {
      "surface_form": "kus",
      "lemma": "ku",
      "grammar": "nominative singular feminine noun",
      "senses_attested_in_panel": [],
      "theme_lists": []
    },
    {
      "surface_form": "um",
      "lemma": "u",
      "grammar": "accusative singular masculine noun",
      "senses_attested_in_panel": [],
      "theme_lists": []
    },
    {
      "surface_form": "ākaras",
      "lemma": "ākṛ",
      "grammar": "nominative singular masculine noun",
      "senses_attested_in_panel": [],
      "theme_lists": []
    }
  ],
  "intertextual_panel": [
    {
      "verse": "10.33",
      "type": "thematic-similarity",
      "score": 0.8682,
      "feature_breakdown": {
        "cosine": 0.8482,
        "theme_graph": 0.0,
        "vocative": 0.0,
        "substring": 0.0,
        "lemma_overlap": 2.2456,
        "stem_prefix": 2.0
      }
    },
    {
      "verse": "18.74",
      "type": "thematic-similarity",
      "score": 0.8674,
      "feature_breakdown": {
        "cosine": 0.8574,
        "theme_graph": 0.0,
        "vocative": 0.0,
        "substring": 0.0,
        "lemma_overlap": 2.2456,
        "stem_prefix": 1.0
      }
    },
    {
      "verse": "10.24",
      "type": "thematic-similarity",
      "score": 0.8639,
      "feature_breakdown": {
        "cosine": 0.8439,
        "theme_graph": 0.0,
        "vocative": 0.0,
        "substring": 0.0,
        "lemma_overlap": 2.2456,
        "stem_prefix": 2.0
      }
    },
    {
      "verse": "10.22",
      "type": "thematic-similarity",
      "score": 0.8623,
      "feature_breakdown": {
        "cosine": 0.8423,
        "theme_graph": 0.0,
        "vocative": 0.0,
        "substring": 0.0,
        "lemma_overlap": 7.2357,
        "stem_prefix": 2.0
      }
    },
    {
      "verse": "10.23",
      "type": "thematic-similarity",
      "score": 0.8617,
      "feature_breakdown": {
        "cosine": 0.8417,
        "theme_graph": 0.0,
        "vocative": 0.0,
        "substring": 0.0,
        "lemma_overlap": 4.3179,
        "stem_prefix": 2.0
      }
    },
    {
      "verse": "9.19",
      "type": "thematic-similarity",
      "score": 0.8615,
      "feature_breakdown": {
        "cosine": 0.8415,
        "theme_graph": 0.0,
        "vocative": 0.0,
        "substring": 0.0,
        "lemma_overlap": 4.3179,
        "stem_prefix": 2.0
      }
    },
    {
      "verse": "2.4",
      "type": "thematic-similarity",
      "score": 0.8586,
      "feature_breakdown": {
        "cosine": 0.8386,
        "theme_graph": 0.0,
        "vocative": 0.0,
        "substring": 0.0,
        "lemma_overlap": 4.3179,
        "stem_prefix": 2.0
      }
    },
    {
      "verse": "10.30",
      "type": "thematic-similarity",
      "score": 0.8575,
      "feature_breakdown": {
        "cosine": 0.8475,
        "theme_graph": 0.0,
        "vocative": 0.0,
        "substring": 0.0,
        "lemma_overlap": 2.2456,
        "stem_prefix": 1.0
      }
    }
  ],
  "doctrinal_projections": {
    "advaita": {
      "reading_summary": "(reading summary extraction forthcoming in next-pass build)",
      "key_cross_references": [],
      "witness_passages": [
        "shankara_10.35",
        "anandgiri_10.35"
      ],
      "score": 0.5
    },
    "viśiṣṭādvaita": {
      "reading_summary": "(reading summary extraction forthcoming in next-pass build)",
      "key_cross_references": [],
      "witness_passages": [
        "ramanuja_10.35",
        "vedantadeshika_10.35"
      ],
      "score": 0.5
    },
    "dvaita": {
      "reading_summary": "(reading summary extraction forthcoming in next-pass build)",
      "key_cross_references": [],
      "witness_passages": [
        "madhva_10.35",
        "jayatirtha_10.35"
      ],
      "score": 0.5
    },
    "śuddhādvaita": {
      "reading_summary": "(reading summary extraction forthcoming in next-pass build)",
      "key_cross_references": [],
      "witness_passages": [
        "vallabha_10.35"
      ],
      "score": 0.5
    },
    "bhakti": {
      "reading_summary": "(reading summary extraction forthcoming in next-pass build)",
      "key_cross_references": [],
      "witness_passages": [
        "sridhara_10.35"
      ],
      "score": 0.5
    },
    "advaita-bhakti": {
      "reading_summary": "(reading summary extraction forthcoming in next-pass build)",
      "key_cross_references": [],
      "witness_passages": [
        "madhusudan_10.35"
      ],
      "score": 0.5
    }
  },
  "prosodic_information": {
    "meter": "anuṣṭubh",
    "meter_shift_from_previous": false,
    "meter_shift_to_next": false,
    "pragmatic_context": {
      "vocative": "",
      "preceding_question": "",
      "following_response": ""
    }
  },
  "theme_list_memberships": [],
  "audit_trail": {
    "substrate_version": "v2.6-frozen",
    "fitted_weights": {
      "a": 1.0,
      "b": 0.01,
      "e_v": 0.005,
      "z": 0.2,
      "h": 0.0,
      "th": 0.01
    },
    "corpus_provenance": {
      "mūla": "Belvalkar critical edition (BORI 1947), via Ambuda multi-witness",
      "panel_witnesses": [
        "bg-mula",
        "bg-shankara",
        "bg-ramanuja",
        "bg-madhva",
        "bg-vedantadeshika",
        "bg-vallabha",
        "bg-jayatirtha",
        "bg-anandgiri",
        "bg-sridhara",
        "bg-madhusudan"
      ]
    },
    "extraction_date": "2026-04-21",
    "score_methodology_documented_at": "Paper 1, Section II.B"
  }
}