{
  "verse_id": "2.38",
  "mūla": {
    "devanāgarī": "सुख-दुःखे समे कृत्वा लाभालाभौ जयाजयौ | ततो युद्धाय युज्यस्व नैवं पापम् अवाप्स्यसि",
    "iast": "sukha-duḥkhe same kṛtvā lābhālābhau jayājayau | tato yuddhāya yujyasva naivaṃ pāpam avāpsyasi",
    "chapter_position": "Chapter 2 (Sāṅkhya-Yoga (The Yoga of Knowledge)), verse 38",
    "speaker": "Krishna",
    "addressed_to": "Arjuna"
  },
  "word_by_word": [
    {
      "surface_form": "sukha",
      "lemma": "sukhi",
      "grammar": "vocative singular masculine noun",
      "senses_attested_in_panel": [],
      "theme_lists": [
        "सुख-दुःख"
      ]
    },
    {
      "surface_form": "dus",
      "lemma": "dus",
      "grammar": "nominative singular masculine noun",
      "senses_attested_in_panel": [],
      "theme_lists": []
    },
    {
      "surface_form": "khe",
      "lemma": "khan",
      "grammar": "locative singular neuter noun",
      "senses_attested_in_panel": [],
      "theme_lists": []
    },
    {
      "surface_form": "same",
      "lemma": "sam",
      "grammar": "locative singular masculine noun",
      "senses_attested_in_panel": [],
      "theme_lists": []
    },
    {
      "surface_form": "kṛtvā",
      "lemma": "kṛ",
      "grammar": "nominative singular masculine noun",
      "senses_attested_in_panel": [
        {
          "sense": "रागद्वेषावप्यकृत्वेत्येतत्",
          "school": "advaita",
          "weight": 0.8,
          "witnesses": [
            "shankara",
            "anandgiri"
          ]
        },
        {
          "sense": "तत्साधनक्रियाभूतौ लाभालाभौ जयाजयौ",
          "school": "śuddhādvaita",
          "weight": 0.8,
          "witnesses": [
            "vallabha"
          ]
        },
        {
          "sense": "तथा तयोः कारणभूतौ यौ लाभालाभावपि तयोरपि कारणभूतौ जयाजयावपि समौ कृत्वा एतेषां समत्वे कारणं हर्षविषादराहित्यम्",
          "school": "bhakti",
          "weight": 0.8,
          "witnesses": [
            "sridhara"
          ]
        }
      ],
      "theme_lists": []
    },
    {
      "surface_form": "lābhās",
      "lemma": "labh",
      "grammar": "nominative plural masculine noun",
      "senses_attested_in_panel": [],
      "theme_lists": []
    },
    {
      "surface_form": "lābhau",
      "lemma": "labh",
      "grammar": "nominative dual masculine noun",
      "senses_attested_in_panel": [],
      "theme_lists": []
    },
    {
      "surface_form": "jayās",
      "lemma": "ji",
      "grammar": "nominative plural masculine noun",
      "senses_attested_in_panel": [],
      "theme_lists": []
    },
    {
      "surface_form": "jayau",
      "lemma": "ji",
      "grammar": "nominative dual masculine noun",
      "senses_attested_in_panel": [],
      "theme_lists": []
    },
    {
      "surface_form": "tatas",
      "lemma": "tatas",
      "grammar": "nominative singular masculine noun",
      "senses_attested_in_panel": [],
      "theme_lists": []
    },
    {
      "surface_form": "yuddhāya",
      "lemma": "yudh",
      "grammar": "dative singular masculine noun",
      "senses_attested_in_panel": [
        {
          "sense": "युज्यस्व घटस्व",
          "school": "advaita",
          "weight": 0.8,
          "witnesses": [
            "shankara",
            "anandgiri"
          ]
        },
        {
          "sense": "युज्यस्व",
          "school": "śuddhādvaita",
          "weight": 0.8,
          "witnesses": [
            "vallabha"
          ]
        },
        {
          "sense": "युज्यस्व संनद्धो भव",
          "school": "advaita-bhakti",
          "weight": 0.8,
          "witnesses": [
            "madhusudan"
          ]
        }
      ],
      "theme_lists": []
    },
    {
      "surface_form": "yujyasva",
      "lemma": "yuj",
      "grammar": "2nd person singular imperative passive verb",
      "senses_attested_in_panel": [
        {
          "sense": "घटस्व। न एवं युद्धं कुर्वन् पापम् अवाप्स्यसि । इत्येष उपदेशः प्रासङ्गिकः।। शोकमोहापनयनाय लौकिको न्यायः स्वधर्ममपि चावेक",
          "school": "advaita",
          "weight": 0.8,
          "witnesses": [
            "shankara"
          ]
        },
        {
          "sense": "। एवं कृतेऽनुद्देशतस्त्वं पापं न प्राप्स्यसि।",
          "school": "śuddhādvaita",
          "weight": 0.8,
          "witnesses": [
            "vallabha"
          ]
        },
        {
          "sense": "सन्नद्धो भव",
          "school": "bhakti",
          "weight": 0.8,
          "witnesses": [
            "sridhara"
          ]
        },
        {
          "sense": "संनद्धो भव",
          "school": "advaita-bhakti",
          "weight": 0.8,
          "witnesses": [
            "madhusudan"
          ]
        }
      ],
      "theme_lists": []
    },
    {
      "surface_form": "na",
      "lemma": "na",
      "grammar": "vocative singular neuter noun",
      "senses_attested_in_panel": [],
      "theme_lists": [
        "अकीर्तिं चापि भूतानि कथयिष्यन्ति तेऽव्ययाम्",
        "अनार्यजुष्टम्"
      ]
    },
    {
      "surface_form": "evam",
      "lemma": "eva",
      "grammar": "accusative singular masculine noun",
      "senses_attested_in_panel": [],
      "theme_lists": []
    },
    {
      "surface_form": "pāpam",
      "lemma": "pāpa",
      "grammar": "accusative singular masculine noun",
      "senses_attested_in_panel": [
        {
          "sense": "अवाप्स्यसि",
          "school": "advaita",
          "weight": 0.8,
          "witnesses": [
            "shankara"
          ]
        },
        {
          "sense": "अवाप्स्यसि पापं दुःखरूपं संसारं न अवाप्स्यसि",
          "school": "viśiṣṭādvaita",
          "weight": 0.8,
          "witnesses": [
            "ramanuja"
          ]
        }
      ],
      "theme_lists": []
    },
    {
      "surface_form": "ava",
      "lemma": "u",
      "grammar": "vocative singular masculine noun",
      "senses_attested_in_panel": [],
      "theme_lists": []
    },
    {
      "surface_form": "āpsyasi",
      "lemma": "āp",
      "grammar": "2nd person singular simple future active verb",
      "senses_attested_in_panel": [],
      "theme_lists": []
    }
  ],
  "intertextual_panel": [
    {
      "verse": "12.18",
      "type": "long-distance thematic echo",
      "score": 0.9102,
      "feature_breakdown": {
        "cosine": 0.8243,
        "theme_graph": 1.0,
        "vocative": 0.0,
        "substring": 0.0797,
        "lemma_overlap": 17.9399,
        "stem_prefix": 6.0
      }
    },
    {
      "verse": "6.7",
      "type": "cross-chapter thematic parallel",
      "score": 0.9093,
      "feature_breakdown": {
        "cosine": 0.8334,
        "theme_graph": 1.0,
        "vocative": 0.0,
        "substring": 0.0797,
        "lemma_overlap": 16.0569,
        "stem_prefix": 5.0
      }
    },
    {
      "verse": "2.33",
      "type": "near-cluster echo",
      "score": 0.9044,
      "feature_breakdown": {
        "cosine": 0.8444,
        "theme_graph": 0.0,
        "vocative": 0.0,
        "substring": 0.0,
        "lemma_overlap": 15.4725,
        "stem_prefix": 6.0
      }
    },
    {
      "verse": "18.8",
      "type": "lemma-family resonance",
      "score": 0.9032,
      "feature_breakdown": {
        "cosine": 0.8432,
        "theme_graph": 0.0,
        "vocative": 0.0,
        "substring": 0.0,
        "lemma_overlap": 15.0175,
        "stem_prefix": 6.0
      }
    },
    {
      "verse": "12.13",
      "type": "long-distance thematic echo",
      "score": 0.9015,
      "feature_breakdown": {
        "cosine": 0.8315,
        "theme_graph": 1.0,
        "vocative": 0.0,
        "substring": 0.0,
        "lemma_overlap": 16.5912,
        "stem_prefix": 6.0
      }
    },
    {
      "verse": "15.5",
      "type": "long-distance thematic echo",
      "score": 0.9007,
      "feature_breakdown": {
        "cosine": 0.8366,
        "theme_graph": 1.0,
        "vocative": 0.0,
        "substring": 0.0709,
        "lemma_overlap": 13.3784,
        "stem_prefix": 4.0
      }
    },
    {
      "verse": "13.20",
      "type": "long-distance thematic echo",
      "score": 0.8928,
      "feature_breakdown": {
        "cosine": 0.8286,
        "theme_graph": 1.0,
        "vocative": 0.0,
        "substring": 0.0709,
        "lemma_overlap": 11.9218,
        "stem_prefix": 4.0
      }
    },
    {
      "verse": "6.22",
      "type": "lemma-family resonance",
      "score": 0.8914,
      "feature_breakdown": {
        "cosine": 0.8414,
        "theme_graph": 0.0,
        "vocative": 0.0,
        "substring": 0.0,
        "lemma_overlap": 15.0296,
        "stem_prefix": 5.0
      }
    }
  ],
  "doctrinal_projections": {
    "advaita": {
      "reading_summary": "(reading summary extraction pending; ENABLE_READING_SUMMARIES=true to generate)",
      "key_cross_references": [],
      "witness_passages": [
        "shankara_2.38",
        "anandgiri_2.38"
      ],
      "score": 0.5,
      "divergence_note": "For Śaṅkara, samatva (equanimity) here is purely a removal of rāga-dveṣa — it carries no intrinsic soteriological weight and is explicitly subordinate to jñāna. The injunction 'fight' is instrumental, not the point."
    },
    "viśiṣṭādvaita": {
      "reading_summary": "(reading summary extraction pending; ENABLE_READING_SUMMARIES=true to generate)",
      "key_cross_references": [],
      "witness_passages": [
        "ramanuja_2.38",
        "vedantadeshika_2.38"
      ],
      "score": 0.5,
      "divergence_note": "Unlike Śaṅkara's demotion to incidental advice, Rāmānuja treats karma-yoga as a full-fledged liberation path; samatva here is the dispositional condition that makes service to Bhagavān (kainkarya) possible."
    },
    "dvaita": {
      "reading_summary": "(reading summary extraction pending; ENABLE_READING_SUMMARIES=true to generate)",
      "key_cross_references": [],
      "witness_passages": [
        "madhva_2.38",
        "jayatirtha_2.38"
      ],
      "score": 0.5,
      "divergence_note": "Dvaita resists any reading in which samatva implies ontological levelling of the pairs; real duality is preserved, and equanimity is volitional surrender to Hari's will, not metaphysical indifference."
    },
    "śuddhādvaita": {
      "reading_summary": "(reading summary extraction pending; ENABLE_READING_SUMMARIES=true to generate)",
      "key_cross_references": [],
      "witness_passages": [
        "vallabha_2.38"
      ],
      "score": 0.5,
      "divergence_note": "Vallabha's samatva is not Śaṅkara's negation of rāga-dveṣa nor Rāmānuja's undisturbed-duty; it is the rapturous recognition that all pairs are Kṛṣṇa's prasāda and therefore equally sacred — a distinctly Puṣṭi-mārga move."
    },
    "bhakti": {
      "reading_summary": "(reading summary extraction pending; ENABLE_READING_SUMMARIES=true to generate)",
      "key_cross_references": [],
      "witness_passages": [
        "sridhara_2.38"
      ],
      "score": 0.5,
      "divergence_note": "Śrīdhara's distinctive contribution is the layered causal analysis: samatva must be applied at all three levels (result, proximate cause, ultimate cause), not merely at the emotional surface — making his reading more structurally thorough than those that stop at rāga-dveṣa."
    },
    "advaita-bhakti": {
      "reading_summary": "(reading summary extraction pending; ENABLE_READING_SUMMARIES=true to generate)",
      "key_cross_references": [],
      "witness_passages": [
        "madhusudan_2.38"
      ],
      "score": 0.5,
      "divergence_note": "Madhusūdana's synthesis is the most juridically complete: he resolves the apparent contradiction between the earlier 'you will attain heaven if slain' (2.37) and this verse's niṣkāma injunction by showing they operate at different logical levels — anusaṅgika-phala (incidental fruit) vs. niṣkāma-dharma (duty-without-intention)."
    }
  },
  "prosodic_information": {
    "meter": "other",
    "meter_shift_from_previous": true,
    "meter_shift_to_next": true,
    "pragmatic_context": {
      "vocative": "",
      "preceding_question": "",
      "following_response": ""
    }
  },
  "theme_list_memberships": [
    {
      "list": "अकीर्तिं चापि भूतानि कथयिष्यन्ति तेऽव्ययाम्",
      "role": "supporting",
      "other_verses_in_list": [
        "2.34"
      ]
    },
    {
      "list": "अकीर्तिकरम्",
      "role": "supporting",
      "other_verses_in_list": [
        "2.2"
      ]
    },
    {
      "list": "अनार्यजुष्टम्",
      "role": "supporting",
      "other_verses_in_list": [
        "2.2"
      ]
    },
    {
      "list": "अस्वर्ग्यम्",
      "role": "supporting",
      "other_verses_in_list": [
        "2.2"
      ]
    },
    {
      "list": "त्यक्त्वोत्तिष्ठ परंतप",
      "role": "supporting",
      "other_verses_in_list": [
        "2.3"
      ]
    },
    {
      "list": "सुख-दुःख",
      "role": "supporting",
      "other_verses_in_list": [
        "2.14",
        "6.7",
        "12.13",
        "12.18",
        "13.20",
        "15.5"
      ]
    }
  ],
  "audit_trail": {
    "substrate_version": "v2.6-frozen",
    "fitted_weights": {
      "a": 1.0,
      "b": 0.01,
      "e_v": 0.005,
      "z": 0.2,
      "h": 0.0,
      "th": 0.01
    },
    "corpus_provenance": {
      "mūla": "Belvalkar critical edition (BORI 1947), via Ambuda multi-witness",
      "panel_witnesses": [
        "bg-mula",
        "bg-shankara",
        "bg-ramanuja",
        "bg-madhva",
        "bg-vedantadeshika",
        "bg-vallabha",
        "bg-jayatirtha",
        "bg-anandgiri",
        "bg-sridhara",
        "bg-madhusudan"
      ]
    },
    "extraction_date": "2026-04-21",
    "score_methodology_documented_at": "Paper 1, Section II.B"
  },
  "so_what_questions": [
    {
      "id": "sq1",
      "question": "Śaṅkara calls this verse 'incidental instruction' (prāsaṅgika upadeśa) and not the central teaching — so what does it mean that Kṛṣṇa embeds a workaround for Arjuna's grief before the real argument has even begun? Is the equanimity being taught here genuine transformation or a therapeutic bridge?",
      "target_schools": [
        "advaita"
      ]
    },
    {
      "id": "sq2",
      "question": "Rāmānuja reads 'you will not incur pāpa' as 'you will be released from saṃsāra' — so what is the relationship between moral innocence and liberation in Viśiṣṭādvaita? Can a karma-yogi act wrongly in terms of outcome yet remain soteriologically clean?",
      "target_schools": [
        "viśiṣṭādvaita"
      ]
    },
    {
      "id": "sq3",
      "question": "Śrīdhara insists that samatva must be applied at all three causal levels — result, proximate cause, ultimate cause — not just at the feeling-surface. So what happens to a practitioner who achieves emotional equanimity (no harṣa-viṣāda) but remains subtly attached to the outcome two levels below? Is partial samatva spiritually dangerous?",
      "target_schools": [
        "bhakti"
      ]
    },
    {
      "id": "sq4",
      "question": "Vallabha's frame makes all pairs — victory and defeat equally — Kṛṣṇa's prasāda. But the verse also says 'fight' — a specific action with a specific opponent. So what distinguishes Puṣṭi-mārga equanimity from quietism or indifference to outcome? How does anuddea (non-purposive action) coexist with strategic excellence on the battlefield?",
      "target_schools": [
        "śuddhādvaita"
      ]
    },
    {
      "id": "sq5",
      "question": "Madhusūdana distinguishes two types of pāpa that the niṣkāma fighter avoids simultaneously — the sin of violent action and the sin of omission. So what does this double-escape structure reveal about how karma-theory actually works: is pāpa located in the action, in the intention, or in the relationship between the two?",
      "target_schools": [
        "advaita-bhakti"
      ]
    },
    {
      "id": "sq6",
      "question": "Across all six schools, the verse links samatva explicitly to legal innocence ('you will not incur pāpa') — not to liberation, bliss, or proximity to God, but to exemption from moral debt. Why does Kṛṣṇa reach first for the juridical frame rather than the soteriological one? What does that sequencing reveal about where Arjuna actually is?",
      "target_schools": [
        "advaita",
        "viśiṣṭādvaita",
        "dvaita",
        "śuddhādvaita",
        "bhakti",
        "advaita-bhakti"
      ]
    },
    {
      "id": "sq7",
      "question": "The verse pairs sukha-duḥkha with lābha-alābha and jaya-ajaya — three nested doublings, not one. None of the commentators treats these three pairs as identical. What is the doctrinal logic for this gradation, and is the innermost pair (victory-defeat) the hardest for a warrior to hold in samatva because it is most identity-constituting?",
      "target_schools": [
        "advaita",
        "viśiṣṭādvaita",
        "bhakti"
      ]
    }
  ],
  "everyday_applications": {
    "advaita": "Before entering a high-stakes review or negotiation, bracket the outcome mentally — not by suppressing the desire to win but by recognizing the reviewing self as distinct from the outcome-accumulating persona. Śaṅkara's 'remove rāga and dveṣa themselves' means: check whether you are entering the room as the person who needs a particular result, or as the person who acts rightly regardless. The task is not emotional flatness but the removal of the investment that would make you argue against your better judgment to protect a preferred conclusion.",
    "viśiṣṭādvaita": "When you are required to give difficult feedback — to a report, a student, a family member — do so with aviḍkrta-buddhi (undisturbed intelligence): neither softening the truth because you fear their pain (that is attachment to their pleasure) nor sharpening it to prove your authority (that is attachment to your victory). Rāmānuja's kārya-buddhi means: act because the relationship and the role require it, not because the outcome will confirm your competence. The Viśiṣṭādvaita practitioner trusts that honest service is itself the liberation-work, regardless of how it lands.",
    "dvaita": "In competitive work — a contested promotion, a legal dispute, a business rivalry — the Dvaita practitioner prepares fully and fights hard, because capability deployed in Hari's service is itself worship. But after each round, the result is handed back: 'this outcome belongs to Hari's dispensation, not to my desert.' This is not fatalism before the contest; it is a specific post-action practice of releasing the result to its sovereign. The distinction between preparation (fully engaged) and attachment to outcome (fully released) is the Dvaita everyday move.",
    "śuddhādvaita": "In creative work — writing, music, design — Vallabha's anuddea (non-purposive action) means making the work for the work's sake, as Kṛṣṇa's play, without orienting every choice toward approval or impact. When a piece lands badly with an audience (alābha, apajaya), the practitioner does not revise the internal vision to match external taste, because the success-failure axis belongs to the līlā-field, not to the creator's identity. The everyday practice is: complete the work fully, then release the reception entirely — not as discipline but as recognition that the reception was never yours to hold.",
    "bhakti": "Śrīdhara's three-level samatva has a direct application in health and illness: equanimity at the surface (not weeping at pain) is easy to perform and easy to fake; equanimity at the proximate cause (not investing in recovery as a measure of self-worth) is harder; equanimity at the deepest level (not orienting one's spiritual practice around being healed) is where harṣa-viṣāda-rāhitya actually lives. The Śrīdhara-informed practitioner checks all three levels — am I calm about this result, about the process that produced it, and about the deeper conditions that made that process possible? — before claiming samatva.",
    "advaita-bhakti": "Madhusūdana's Āpastamba citation offers a precise frame for professional life: do excellent work as your dharma, and allow wealth, recognition, and influence to arise as incidental by-products — the shade and fragrance, not the fruit you planted for. The practical move is to keep the quality bar anchored in the dharma of the role (what does this work require?) rather than the incentive structure (what will this work get me?). This is not indifference to results — the mango tree is still planted carefully — but it means that if the fragrance doesn't come, the planting was not a failure."
  }
}