{
  "verse_id": "4.18",
  "mūla": {
    "devanāgarī": "कर्मण्य् अकर्म यः पश्येद् अकर्मणि च कर्म यः | स बुद्धिमान् मनुष्येषु स युक्तः कृत्स्न-कर्म-कृत्",
    "iast": "karmaṇy akarma yaḥ paśyed akarmaṇi ca karma yaḥ | sa buddhimān manuṣyeṣu sa yuktaḥ kṛtsna-karma-kṛt",
    "chapter_position": "Chapter 4 (Jñāna-Karma-Sannyāsa-Yoga (The Yoga of Renunciation of Action in Knowledge)), verse 18",
    "speaker": "Krishna",
    "addressed_to": "Arjuna"
  },
  "word_by_word": [
    {
      "surface_form": "karmaṇi",
      "lemma": "karman",
      "grammar": "locative singular neuter noun",
      "senses_attested_in_panel": [
        {
          "sense": "क्रियते इति कर्म व्यापारमात्रम् तस्मिन् कर्मणि अकर्म कर्माभावं",
          "school": "advaita",
          "weight": 0.5,
          "witnesses": [
            "shankara",
            "anandgiri"
          ]
        },
        {
          "sense": "क्रियमाणे",
          "school": "viśiṣṭādvaita",
          "weight": 0.5,
          "witnesses": [
            "ramanuja",
            "vedantadeshika"
          ]
        },
        {
          "sense": "क्रियमाणे सत्यकर्म",
          "school": "dvaita",
          "weight": 1.0,
          "witnesses": [
            "madhva"
          ]
        },
        {
          "sense": "यज्ञकर्मणि स्वक्रियानिर्वर्त्त्ये उक्तप्रकारके कर्मणीत्युपलक्षणं सर्वत्रैव अकर्म निर्बन्धकत्वं समं ब्रह्म वा साङ्ख्ययोग",
          "school": "śuddhādvaita",
          "weight": 1.0,
          "witnesses": [
            "vallabha"
          ]
        },
        {
          "sense": "विषये अकर्म कर्मेदं न भवतीति",
          "school": "bhakti",
          "weight": 1.0,
          "witnesses": [
            "sridhara"
          ]
        },
        {
          "sense": "देहेन्द्रियादिव्यापारे विहिते प्रतिषिद्धे",
          "school": "advaita-bhakti",
          "weight": 1.0,
          "witnesses": [
            "madhusudan"
          ]
        }
      ],
      "theme_lists": [
        "अकर्मणि च कर्म यः",
        "कर्मणि"
      ]
    },
    {
      "surface_form": "akarma",
      "lemma": "akarman",
      "grammar": "vocative singular neuter noun",
      "senses_attested_in_panel": [
        {
          "sense": "कर्माभावं",
          "school": "advaita",
          "weight": 0.5,
          "witnesses": [
            "shankara",
            "anandgiri"
          ]
        },
        {
          "sense": "शब्देन अत्र कर्मेतरत् प्रस्तुतम् आत्मज्ञानम् उच्यते",
          "school": "viśiṣṭādvaita",
          "weight": 0.5,
          "witnesses": [
            "ramanuja",
            "vedantadeshika"
          ]
        },
        {
          "sense": "णि सुप्त्यादावकरणावस्थायाम्",
          "school": "dvaita",
          "weight": 0.5,
          "witnesses": [
            "madhva",
            "jayatirtha"
          ]
        },
        {
          "sense": "निर्बन्धकत्वं समं ब्रह्म वा साङ्ख्ययोगमार्गीयः सन् पश्येत् भावयेत् सर्वं खल्विदं ब्रह्म तज्जलानिति शान्त उपासीत छा.उ.3",
          "school": "śuddhādvaita",
          "weight": 1.0,
          "witnesses": [
            "vallabha"
          ]
        },
        {
          "sense": "कर्मेदं न भवतीति",
          "school": "bhakti",
          "weight": 1.0,
          "witnesses": [
            "sridhara"
          ]
        },
        {
          "sense": "णि च स्वप्रकाशे दृग्वस्तुनि कल्पितं कर्म दृश्यं मायामयं न परमार्थसत् दृग्दृश्ययोः संबन्धानुपपत्तेःयस्तु सर्वाणि भूतान्या",
          "school": "advaita-bhakti",
          "weight": 1.0,
          "witnesses": [
            "madhusudan"
          ]
        }
      ],
      "theme_lists": [
        "अकर्म",
        "अकर्मणि च कर्म यः"
      ]
    },
    {
      "surface_form": "yas",
      "lemma": "ī",
      "grammar": "nominative plural masculine noun",
      "senses_attested_in_panel": [
        {
          "sense": "तम् यतः पण्डितोऽपि अहं करोमि इति मन्यते",
          "school": "advaita",
          "weight": 0.5,
          "witnesses": [
            "shankara",
            "anandgiri"
          ]
        },
        {
          "sense": "मिन्ननुष्ठीयमाने तदन्यज्ञानस्य दुष्करत्वात् अन्यस्मिंश्चानुसन्धीयमाने तदन्यस्य कर्तुमशक्यत्वात् अन्यतरत्रेतरदर्शने",
          "school": "viśiṣṭādvaita",
          "weight": 1.0,
          "witnesses": [
            "vedantadeshika"
          ]
        },
        {
          "sense": "त्वात्मरतिरेव स्यात् इत्यादिना",
          "school": "bhakti",
          "weight": 1.0,
          "witnesses": [
            "sridhara"
          ]
        },
        {
          "sense": "तु सर्वाणि भूतान्यात्मन्येवानुपश्यति",
          "school": "advaita-bhakti",
          "weight": 1.0,
          "witnesses": [
            "madhusudan"
          ]
        }
      ],
      "theme_lists": []
    },
    {
      "surface_form": "paśyet",
      "lemma": "dṛś",
      "grammar": "3rd person singular optative active verb",
      "senses_attested_in_panel": [
        {
          "sense": "अकर्मणि",
          "school": "advaita",
          "weight": 0.5,
          "witnesses": [
            "shankara",
            "anandgiri"
          ]
        },
        {
          "sense": "अकर्मणि",
          "school": "viśiṣṭādvaita",
          "weight": 0.5,
          "witnesses": [
            "ramanuja",
            "vedantadeshika"
          ]
        },
        {
          "sense": "विष्णोरेव कर्म नाहं चित्प्रतिबिम्बः किञ्चित्करोमीति",
          "school": "dvaita",
          "weight": 0.5,
          "witnesses": [
            "madhva",
            "jayatirtha"
          ]
        },
        {
          "sense": "भावयेत् सर्वं खल्विदं ब्रह्म तज्जलानिति शान्त उपासीत छा.उ.3",
          "school": "śuddhādvaita",
          "weight": 1.0,
          "witnesses": [
            "vallabha"
          ]
        },
        {
          "sense": "तस्य ज्ञानहेतुत्वेन बन्धकत्वाभावात्",
          "school": "bhakti",
          "weight": 1.0,
          "witnesses": [
            "sridhara"
          ]
        },
        {
          "sense": "पश्यति",
          "school": "advaita-bhakti",
          "weight": 1.0,
          "witnesses": [
            "madhusudan"
          ]
        }
      ],
      "theme_lists": [
        "कर्मण्यकर्म यः पश्येत्"
      ]
    },
    {
      "surface_form": "akarmaṇi",
      "lemma": "akarman",
      "grammar": "locative singular neuter noun",
      "senses_attested_in_panel": [
        {
          "sense": "च कर्माभावे कर्तृतन्त्रत्वात् प्रवृत्तिनिवृत्त्योः वस्तु अप्राप्यैव हि सर्व एव क्रियाकारकादिव्यवहारः अविद्याभूमौ एव कर्",
          "school": "advaita",
          "weight": 0.5,
          "witnesses": [
            "shankara",
            "anandgiri"
          ]
        },
        {
          "sense": "च आत्मज्ञाने वर्तमान एव यः कर्म पश्येत्।किम् उक्तं भवतिक्रियमाणम् एव कर्म आत्मयाथात्म्यानुसन्धानेन ज्ञानाकारं यः पश्येत",
          "school": "viśiṣṭādvaita",
          "weight": 0.5,
          "witnesses": [
            "ramanuja",
            "vedantadeshika"
          ]
        },
        {
          "sense": "सुप्त्यादावकरणावस्थायाम्",
          "school": "dvaita",
          "weight": 1.0,
          "witnesses": [
            "madhva"
          ]
        },
        {
          "sense": "च विहिताकरणे कर्म यः पश्येत्तस्य प्रत्यवायोत्पादकत्वेन बन्धहेतुत्वात् मनुष्येषु कर्मकुर्वाणेषु स बुद्धिमान्व्यवसायात्मक",
          "school": "bhakti",
          "weight": 1.0,
          "witnesses": [
            "sridhara"
          ]
        },
        {
          "sense": "च स्वप्रकाशे दृग्वस्तुनि कल्पितं कर्म दृश्यं मायामयं न परमार्थसत् दृग्दृश्ययोः संबन्धानुपपत्तेःयस्तु सर्वाणि भूतान्यात्",
          "school": "advaita-bhakti",
          "weight": 1.0,
          "witnesses": [
            "madhusudan"
          ]
        }
      ],
      "theme_lists": [
        "अकर्मणि च कर्म यः"
      ]
    },
    {
      "surface_form": "ca",
      "lemma": "ca",
      "grammar": "vocative singular masculine noun",
      "senses_attested_in_panel": [
        {
          "sense": "कर्माभावे कर्तृतन्त्रत्वात् प्रवृत्तिनिवृत्त्योः वस्तु अप्राप्यैव हि सर्व",
          "school": "advaita",
          "weight": 0.5,
          "witnesses": [
            "shankara",
            "anandgiri"
          ]
        },
        {
          "sense": "्यते। कर्मणि क्रियमाणे एव आत्मज्ञानं य पश्येत् अकर्मणि च आत्मज्ञाने वर्तमान एव यः कर्म पश्येत्।किम् उक्तं भवतिक्रियमाणम्",
          "school": "viśiṣṭādvaita",
          "weight": 0.5,
          "witnesses": [
            "ramanuja",
            "vedantadeshika"
          ]
        },
        {
          "sense": "ित्प्रतिबिम्बः किञ्चित्करोमीति",
          "school": "dvaita",
          "weight": 0.5,
          "witnesses": [
            "madhva",
            "jayatirtha"
          ]
        },
        {
          "sense": "भावयेत् इत्याचार्योक्तेश्च",
          "school": "śuddhādvaita",
          "weight": 1.0,
          "witnesses": [
            "vallabha"
          ]
        },
        {
          "sense": "विहिताकरणे कर्म",
          "school": "bhakti",
          "weight": 1.0,
          "witnesses": [
            "sridhara"
          ]
        },
        {
          "sense": "अहं करोमीति धर्माध्यासेनात्मन्यारोपिरो नौस्थेनाचलत्सु तटस्थवृक्षादिषु समारोपिते चलनइवाकर्त्रात्मस्वरूपालोचनेन वस्तुतः क",
          "school": "advaita-bhakti",
          "weight": 1.0,
          "witnesses": [
            "madhusudan"
          ]
        }
      ],
      "theme_lists": [
        "अकर्मणि च कर्म यः",
        "नैव तस्य कृतेनार्थो नाकृतेनेह कश्चन"
      ]
    },
    {
      "surface_form": "karma",
      "lemma": "karman",
      "grammar": "vocative singular neuter noun",
      "senses_attested_in_panel": [
        {
          "sense": "णि क्रियते इति कर्म व्यापारमात्रम् तस्मिन् कर्मणि अकर्म कर्माभावं",
          "school": "advaita",
          "weight": 0.5,
          "witnesses": [
            "shankara",
            "anandgiri"
          ]
        },
        {
          "sense": "शब्देन अत्र कर्मेतरत् प्रस्तुतम् आत्मज्ञानम् उच्यते",
          "school": "viśiṣṭādvaita",
          "weight": 0.5,
          "witnesses": [
            "ramanuja",
            "vedantadeshika"
          ]
        },
        {
          "sense": "ादिस्वरूपमाह कर्मणीति",
          "school": "dvaita",
          "weight": 0.5,
          "witnesses": [
            "madhva",
            "jayatirtha"
          ]
        },
        {
          "sense": "णो याथात्म्यं स्वयं दर्शयन् क्रियाद्वैतमाह कर्मण्यकर्मेति",
          "school": "śuddhādvaita",
          "weight": 1.0,
          "witnesses": [
            "vallabha"
          ]
        },
        {
          "sense": "ादीनां दुर्विज्ञेयत्वं दर्शयन्नाह कर्मण्यकर्मेति",
          "school": "bhakti",
          "weight": 1.0,
          "witnesses": [
            "sridhara"
          ]
        },
        {
          "sense": "ादीनां तत्त्वमिति तदाह कर्मणि देहेन्द्रियादिव्यापारे विहिते प्रतिषिद्धे",
          "school": "advaita-bhakti",
          "weight": 1.0,
          "witnesses": [
            "madhusudan"
          ]
        }
      ],
      "theme_lists": [
        "अकर्म",
        "अकर्मणि च कर्म यः",
        "कर्मणि",
        "कर्मण्यकर्म यः पश्येत्",
        "योगस्थः कुरु कर्माणि"
      ]
    },
    {
      "surface_form": "yas",
      "lemma": "ī",
      "grammar": "nominative plural masculine noun",
      "senses_attested_in_panel": [
        {
          "sense": "तम् यतः पण्डितोऽपि अहं करोमि इति मन्यते",
          "school": "advaita",
          "weight": 0.5,
          "witnesses": [
            "shankara",
            "anandgiri"
          ]
        },
        {
          "sense": "मिन्ननुष्ठीयमाने तदन्यज्ञानस्य दुष्करत्वात् अन्यस्मिंश्चानुसन्धीयमाने तदन्यस्य कर्तुमशक्यत्वात् अन्यतरत्रेतरदर्शने",
          "school": "viśiṣṭādvaita",
          "weight": 1.0,
          "witnesses": [
            "vedantadeshika"
          ]
        },
        {
          "sense": "त्वात्मरतिरेव स्यात् इत्यादिना",
          "school": "bhakti",
          "weight": 1.0,
          "witnesses": [
            "sridhara"
          ]
        },
        {
          "sense": "तु सर्वाणि भूतान्यात्मन्येवानुपश्यति",
          "school": "advaita-bhakti",
          "weight": 1.0,
          "witnesses": [
            "madhusudan"
          ]
        }
      ],
      "theme_lists": []
    },
    {
      "surface_form": "sa",
      "lemma": "sa",
      "grammar": "vocative singular masculine noun",
      "senses_attested_in_panel": [
        {
          "sense": "्मिन् कर्मणि अकर्म कर्माभावं",
          "school": "advaita",
          "weight": 0.5,
          "witnesses": [
            "shankara",
            "anandgiri"
          ]
        },
        {
          "sense": "्तुतम् आत्मज्ञानम् उच्यते",
          "school": "viśiṣṭādvaita",
          "weight": 0.5,
          "witnesses": [
            "ramanuja",
            "vedantadeshika"
          ]
        },
        {
          "sense": "्वरूपमाह कर्मणीति",
          "school": "dvaita",
          "weight": 0.5,
          "witnesses": [
            "madhva",
            "jayatirtha"
          ]
        },
        {
          "sense": "्यैव कर्मणो याथात्म्यं स्वयं दर्शयन् क्रियाद्वैतमाह कर्मण्यकर्मेति",
          "school": "śuddhādvaita",
          "weight": 1.0,
          "witnesses": [
            "vallabha"
          ]
        },
        {
          "sense": "्य ज्ञानहेतुत्वेन बन्धकत्वाभावात्",
          "school": "bhakti",
          "weight": 1.0,
          "witnesses": [
            "sridhara"
          ]
        },
        {
          "sense": "ेनात्मन्यारोपिरो नौस्थेनाचलत्सु तटस्थवृक्षादिषु समारोपिते चलनइवाकर्त्रात्मस्वरूपालोचनेन वस्तुतः कर्माभावं तटस्थवृक्षादिष",
          "school": "advaita-bhakti",
          "weight": 1.0,
          "witnesses": [
            "madhusudan"
          ]
        }
      ],
      "theme_lists": [
        "नैव तस्य कृतेनार्थो नाकृतेनेह कश्चन",
        "फले सक्तो निबध्यते",
        "योगस्थः कुरु कर्माणि",
        "स युक्तः"
      ]
    },
    {
      "surface_form": "buddhim",
      "lemma": "budh",
      "grammar": "accusative singular masculine noun",
      "senses_attested_in_panel": [],
      "theme_lists": []
    },
    {
      "surface_form": "ān",
      "lemma": "a",
      "grammar": "accusative plural masculine noun",
      "senses_attested_in_panel": [],
      "theme_lists": []
    },
    {
      "surface_form": "manuṣi",
      "lemma": "manus",
      "grammar": "locative singular masculine noun",
      "senses_attested_in_panel": [],
      "theme_lists": []
    },
    {
      "surface_form": "eṣu",
      "lemma": "a",
      "grammar": "locative plural masculine noun",
      "senses_attested_in_panel": [],
      "theme_lists": []
    },
    {
      "surface_form": "sa",
      "lemma": "sa",
      "grammar": "vocative singular masculine noun",
      "senses_attested_in_panel": [
        {
          "sense": "्मिन् कर्मणि अकर्म कर्माभावं",
          "school": "advaita",
          "weight": 0.5,
          "witnesses": [
            "shankara",
            "anandgiri"
          ]
        },
        {
          "sense": "्तुतम् आत्मज्ञानम् उच्यते",
          "school": "viśiṣṭādvaita",
          "weight": 0.5,
          "witnesses": [
            "ramanuja",
            "vedantadeshika"
          ]
        },
        {
          "sense": "्वरूपमाह कर्मणीति",
          "school": "dvaita",
          "weight": 0.5,
          "witnesses": [
            "madhva",
            "jayatirtha"
          ]
        },
        {
          "sense": "्यैव कर्मणो याथात्म्यं स्वयं दर्शयन् क्रियाद्वैतमाह कर्मण्यकर्मेति",
          "school": "śuddhādvaita",
          "weight": 1.0,
          "witnesses": [
            "vallabha"
          ]
        },
        {
          "sense": "्य ज्ञानहेतुत्वेन बन्धकत्वाभावात्",
          "school": "bhakti",
          "weight": 1.0,
          "witnesses": [
            "sridhara"
          ]
        },
        {
          "sense": "ेनात्मन्यारोपिरो नौस्थेनाचलत्सु तटस्थवृक्षादिषु समारोपिते चलनइवाकर्त्रात्मस्वरूपालोचनेन वस्तुतः कर्माभावं तटस्थवृक्षादिष",
          "school": "advaita-bhakti",
          "weight": 1.0,
          "witnesses": [
            "madhusudan"
          ]
        }
      ],
      "theme_lists": [
        "नैव तस्य कृतेनार्थो नाकृतेनेह कश्चन",
        "फले सक्तो निबध्यते",
        "योगस्थः कुरु कर्माणि",
        "स युक्तः"
      ]
    },
    {
      "surface_form": "yuktas",
      "lemma": "yuj",
      "grammar": "nominative singular masculine noun",
      "senses_attested_in_panel": [],
      "theme_lists": []
    },
    {
      "surface_form": "kṛtsna",
      "lemma": "kṛtsna",
      "grammar": "vocative singular neuter noun",
      "senses_attested_in_panel": [
        {
          "sense": "कर्मकृत् समस्तकर्मकृच्च सः इति स्तूयते कर्माकर्मणोरितरेतरदर्शी",
          "school": "advaita",
          "weight": 1.0,
          "witnesses": [
            "shankara"
          ]
        },
        {
          "sense": "शास्त्रार्थवित् मनुष्येषु स युक्तः मोक्षार्हः स",
          "school": "viśiṣṭādvaita",
          "weight": 0.5,
          "witnesses": [
            "ramanuja",
            "vedantadeshika"
          ]
        },
        {
          "sense": "कर्मकृत कृत्स्नफलवत्त्वात्",
          "school": "dvaita",
          "weight": 0.5,
          "witnesses": [
            "madhva",
            "jayatirtha"
          ]
        },
        {
          "sense": "कर्मकृच्च तत्कर्मणि सर्वकर्मफलानामानन्दानामन्तर्भूतत्वात्तत्कर्त्ता भवति",
          "school": "śuddhādvaita",
          "weight": 1.0,
          "witnesses": [
            "vallabha"
          ]
        },
        {
          "sense": "कर्मकर्ता च",
          "school": "bhakti",
          "weight": 1.0,
          "witnesses": [
            "sridhara"
          ]
        },
        {
          "sense": "कर्मकृदिति वास्तवधर्मैरेव स्तूयते",
          "school": "advaita-bhakti",
          "weight": 1.0,
          "witnesses": [
            "madhusudan"
          ]
        }
      ],
      "theme_lists": []
    },
    {
      "surface_form": "karma",
      "lemma": "karman",
      "grammar": "vocative singular neuter noun",
      "senses_attested_in_panel": [
        {
          "sense": "णि क्रियते इति कर्म व्यापारमात्रम् तस्मिन् कर्मणि अकर्म कर्माभावं",
          "school": "advaita",
          "weight": 0.5,
          "witnesses": [
            "shankara",
            "anandgiri"
          ]
        },
        {
          "sense": "शब्देन अत्र कर्मेतरत् प्रस्तुतम् आत्मज्ञानम् उच्यते",
          "school": "viśiṣṭādvaita",
          "weight": 0.5,
          "witnesses": [
            "ramanuja",
            "vedantadeshika"
          ]
        },
        {
          "sense": "ादिस्वरूपमाह कर्मणीति",
          "school": "dvaita",
          "weight": 0.5,
          "witnesses": [
            "madhva",
            "jayatirtha"
          ]
        },
        {
          "sense": "णो याथात्म्यं स्वयं दर्शयन् क्रियाद्वैतमाह कर्मण्यकर्मेति",
          "school": "śuddhādvaita",
          "weight": 1.0,
          "witnesses": [
            "vallabha"
          ]
        },
        {
          "sense": "ादीनां दुर्विज्ञेयत्वं दर्शयन्नाह कर्मण्यकर्मेति",
          "school": "bhakti",
          "weight": 1.0,
          "witnesses": [
            "sridhara"
          ]
        },
        {
          "sense": "ादीनां तत्त्वमिति तदाह कर्मणि देहेन्द्रियादिव्यापारे विहिते प्रतिषिद्धे",
          "school": "advaita-bhakti",
          "weight": 1.0,
          "witnesses": [
            "madhusudan"
          ]
        }
      ],
      "theme_lists": [
        "अकर्म",
        "अकर्मणि च कर्म यः",
        "कर्मणि",
        "कर्मण्यकर्म यः पश्येत्",
        "योगस्थः कुरु कर्माणि"
      ]
    },
    {
      "surface_form": "kṛt",
      "lemma": "kṛ",
      "grammar": "nominative singular masculine noun",
      "senses_attested_in_panel": [
        {
          "sense": "स्नकर्मकृत् समस्तकर्मकृच्च सः इति स्तूयते कर्माकर्मणोरितरेतरदर्शी",
          "school": "advaita",
          "weight": 0.5,
          "witnesses": [
            "shankara",
            "anandgiri"
          ]
        },
        {
          "sense": "स्नशास्त्रार्थवित् मनुष्येषु स युक्तः मोक्षार्हः स",
          "school": "viśiṣṭādvaita",
          "weight": 0.5,
          "witnesses": [
            "ramanuja",
            "vedantadeshika"
          ]
        },
        {
          "sense": "स्नकर्मकृत कृत्स्नफलवत्त्वात्",
          "school": "dvaita",
          "weight": 0.5,
          "witnesses": [
            "madhva",
            "jayatirtha"
          ]
        },
        {
          "sense": "स्नकर्मकृच्च तत्कर्मणि सर्वकर्मफलानामानन्दानामन्तर्भूतत्वात्तत्कर्त्ता भवति",
          "school": "śuddhādvaita",
          "weight": 1.0,
          "witnesses": [
            "vallabha"
          ]
        },
        {
          "sense": "स्नकर्मकर्ता च",
          "school": "bhakti",
          "weight": 1.0,
          "witnesses": [
            "sridhara"
          ]
        },
        {
          "sense": "त्वैस्त्रिभिर्धमैः स्तूयते",
          "school": "advaita-bhakti",
          "weight": 1.0,
          "witnesses": [
            "madhusudan"
          ]
        }
      ],
      "theme_lists": []
    }
  ],
  "intertextual_panel": [
    {
      "verse": "13.29",
      "type": "thematic-similarity",
      "score": 0.945,
      "feature_breakdown": {
        "cosine": 0.875,
        "theme_graph": 0.0,
        "vocative": 0.0,
        "substring": 0.0,
        "lemma_overlap": 12.3025,
        "stem_prefix": 7.0
      }
    },
    {
      "verse": "4.17",
      "type": "thematic-similarity",
      "score": 0.9398,
      "feature_breakdown": {
        "cosine": 0.8698,
        "theme_graph": 3.0,
        "vocative": 0.0,
        "substring": 0.0,
        "lemma_overlap": 10.4152,
        "stem_prefix": 4.0
      }
    },
    {
      "verse": "2.47",
      "type": "thematic-similarity",
      "score": 0.9333,
      "feature_breakdown": {
        "cosine": 0.8597,
        "theme_graph": 3.0,
        "vocative": 0.0,
        "substring": 0.0677,
        "lemma_overlap": 7.4176,
        "stem_prefix": 3.0
      }
    },
    {
      "verse": "5.12",
      "type": "thematic-similarity",
      "score": 0.928,
      "feature_breakdown": {
        "cosine": 0.858,
        "theme_graph": 4.0,
        "vocative": 0.0,
        "substring": 0.0,
        "lemma_overlap": 6.0358,
        "stem_prefix": 3.0
      }
    },
    {
      "verse": "3.26",
      "type": "thematic-similarity",
      "score": 0.9256,
      "feature_breakdown": {
        "cosine": 0.8656,
        "theme_graph": 3.0,
        "vocative": 0.0,
        "substring": 0.0,
        "lemma_overlap": 6.8106,
        "stem_prefix": 3.0
      }
    },
    {
      "verse": "6.1",
      "type": "thematic-similarity",
      "score": 0.9157,
      "feature_breakdown": {
        "cosine": 0.8657,
        "theme_graph": 0.0,
        "vocative": 0.0,
        "substring": 0.0,
        "lemma_overlap": 9.0553,
        "stem_prefix": 5.0
      }
    },
    {
      "verse": "18.31",
      "type": "thematic-similarity",
      "score": 0.9155,
      "feature_breakdown": {
        "cosine": 0.8655,
        "theme_graph": 1.0,
        "vocative": 0.0,
        "substring": 0.0,
        "lemma_overlap": 6.4725,
        "stem_prefix": 4.0
      }
    },
    {
      "verse": "2.51",
      "type": "thematic-similarity",
      "score": 0.9126,
      "feature_breakdown": {
        "cosine": 0.8626,
        "theme_graph": 2.0,
        "vocative": 0.0,
        "substring": 0.0,
        "lemma_overlap": 4.7718,
        "stem_prefix": 3.0
      }
    }
  ],
  "doctrinal_projections": {
    "advaita": {
      "reading_summary": "(reading summary extraction forthcoming in next-pass build)",
      "key_cross_references": [],
      "witness_passages": [
        "shankara_4.18",
        "anandgiri_4.18"
      ],
      "score": 0.5
    },
    "viśiṣṭādvaita": {
      "reading_summary": "(reading summary extraction forthcoming in next-pass build)",
      "key_cross_references": [],
      "witness_passages": [
        "ramanuja_4.18",
        "vedantadeshika_4.18"
      ],
      "score": 0.5
    },
    "dvaita": {
      "reading_summary": "(reading summary extraction forthcoming in next-pass build)",
      "key_cross_references": [],
      "witness_passages": [
        "madhva_4.18",
        "jayatirtha_4.18"
      ],
      "score": 0.5
    },
    "śuddhādvaita": {
      "reading_summary": "(reading summary extraction forthcoming in next-pass build)",
      "key_cross_references": [],
      "witness_passages": [
        "vallabha_4.18"
      ],
      "score": 0.5
    },
    "bhakti": {
      "reading_summary": "(reading summary extraction forthcoming in next-pass build)",
      "key_cross_references": [],
      "witness_passages": [
        "sridhara_4.18"
      ],
      "score": 0.5
    },
    "advaita-bhakti": {
      "reading_summary": "(reading summary extraction forthcoming in next-pass build)",
      "key_cross_references": [],
      "witness_passages": [
        "madhusudan_4.18"
      ],
      "score": 0.5
    }
  },
  "prosodic_information": {
    "meter": "other",
    "meter_shift_from_previous": true,
    "meter_shift_to_next": true,
    "pragmatic_context": {
      "vocative": "",
      "preceding_question": "",
      "following_response": ""
    }
  },
  "theme_list_memberships": [
    {
      "list": "अकर्म",
      "role": "supporting",
      "other_verses_in_list": [
        "2.47",
        "3.5",
        "3.8",
        "4.16",
        "4.17",
        "4.23",
        "4.24",
        "5.12",
        "12.17"
      ]
    },
    {
      "list": "अकर्मणि च कर्म यः",
      "role": "supporting",
      "other_verses_in_list": [
        "4.17"
      ]
    },
    {
      "list": "कर्मणि",
      "role": "supporting",
      "other_verses_in_list": [
        "2.47",
        "3.1",
        "3.22",
        "4.16",
        "4.21",
        "14.9",
        "17.26"
      ]
    },
    {
      "list": "कर्मण्यकर्म यः पश्येत्",
      "role": "supporting",
      "other_verses_in_list": [
        "4.17"
      ]
    },
    {
      "list": "जानना",
      "role": "supporting",
      "other_verses_in_list": [
        "3.3",
        "7.12"
      ]
    },
    {
      "list": "नैव तस्य कृतेनार्थो नाकृतेनेह कश्चन",
      "role": "supporting",
      "other_verses_in_list": [
        "3.18"
      ]
    },
    {
      "list": "फले सक्तो निबध्यते",
      "role": "supporting",
      "other_verses_in_list": [
        "2.47",
        "5.12",
        "11.33",
        "12.12"
      ]
    },
    {
      "list": "बुद्धि",
      "role": "supporting",
      "other_verses_in_list": [
        "2.19",
        "2.39",
        "2.41",
        "2.44",
        "2.49",
        "2.50",
        "2.51",
        "2.52",
        "2.53",
        "2.63",
        "2.65",
        "2.66",
        "3.1",
        "3.2",
        "3.3",
        "3.26",
        "3.40",
        "3.42",
        "5.17",
        "5.20",
        "5.28",
        "6.9",
        "6.21",
        "6.43",
        "7.4",
        "7.5",
        "7.10",
        "8.7",
        "10.4",
        "10.10",
        "12.8",
        "12.14",
        "13.5",
        "15.20",
        "18.16",
        "18.17",
        "18.30",
        "18.31",
        "18.32",
        "18.37",
        "18.49",
        "18.57"
      ]
    },
    {
      "list": "मनुष्य",
      "role": "supporting",
      "other_verses_in_list": [
        "1.44",
        "3.23",
        "3.38",
        "4.11",
        "7.3",
        "15.2",
        "18.69"
      ]
    },
    {
      "list": "मेधावी",
      "role": "supporting",
      "other_verses_in_list": [
        "18.10"
      ]
    },
    {
      "list": "युक्त",
      "role": "supporting",
      "other_verses_in_list": [
        "1.14",
        "2.28",
        "2.39",
        "2.50",
        "2.51",
        "2.61",
        "2.64",
        "2.66",
        "3.26",
        "3.36",
        "5.6",
        "5.7",
        "5.8",
        "5.12",
        "5.21",
        "5.23",
        "5.26",
        "6.8",
        "6.14",
        "6.17",
        "6.18",
        "6.29",
        "6.47",
        "7.17",
        "7.18",
        "7.22",
        "7.30",
        "8.8",
        "8.10",
        "8.14",
        "8.27",
        "9.14",
        "9.22",
        "9.28",
        "9.34",
        "10.10",
        "12.1",
        "12.2",
        "15.14",
        "17.5",
        "17.17",
        "18.28",
        "18.51"
      ]
    },
    {
      "list": "युक्तः",
      "role": "supporting",
      "other_verses_in_list": [
        "2.28",
        "3.26",
        "5.12",
        "5.23",
        "6.14",
        "15.14",
        "18.28"
      ]
    },
    {
      "list": "योगस्थः कुरु कर्माणि",
      "role": "supporting",
      "other_verses_in_list": [
        "2.48",
        "3.4",
        "4.16"
      ]
    },
    {
      "list": "स युक्तः",
      "role": "supporting",
      "other_verses_in_list": [
        "5.23"
      ]
    }
  ],
  "audit_trail": {
    "substrate_version": "v2.6-frozen",
    "fitted_weights": {
      "a": 1.0,
      "b": 0.01,
      "e_v": 0.005,
      "z": 0.2,
      "h": 0.0,
      "th": 0.01
    },
    "corpus_provenance": {
      "mūla": "Belvalkar critical edition (BORI 1947), via Ambuda multi-witness",
      "panel_witnesses": [
        "bg-mula",
        "bg-shankara",
        "bg-ramanuja",
        "bg-madhva",
        "bg-vedantadeshika",
        "bg-vallabha",
        "bg-jayatirtha",
        "bg-anandgiri",
        "bg-sridhara",
        "bg-madhusudan"
      ]
    },
    "extraction_date": "2026-04-21",
    "score_methodology_documented_at": "Paper 1, Section II.B"
  }
}